[{"countyFIPS":"18049","pop":19974,"date":"2020-03-01","deaths":0,"County Name":"Fulton County","State":"IN","stateFIPS":"18","case_count":0,"delta":0,"infect_prob":0},{"countyFIPS":"18049","pop":19974,"date":"2020-03-02","deaths":0,"County Name":"Fulton County","State":"IN","stateFIPS":"18","case_count":0,"delta":0,"infect_prob":0},{"countyFIPS":"18049","pop":19974,"date":"2020-03-03","deaths":0,"County Name":"Fulton County","State":"IN","stateFIPS":"18","case_count":0,"delta":0,"infect_prob":0},{"countyFIPS":"18049","pop":19974,"date":"2020-03-04","deaths":0,"County Name":"Fulton County","State":"IN","stateFIPS":"18","case_count":0,"delta":0,"infect_prob":0},{"countyFIPS":"18049","pop":19974,"date":"2020-03-05","deaths":0,"County Name":"Fulton County","State":"IN","stateFIPS":"18","case_count":0,"delta":0,"infect_prob":0},{"countyFIPS":"18049","pop":19974,"date":"2020-03-06","deaths":0,"County Name":"Fulton County","State":"IN","stateFIPS":"18","case_count":0,"delta":0,"infect_prob":0},{"countyFIPS":"18049","pop":19974,"date":"2020-03-07","deaths":0,"County Name":"Fulton County","State":"IN","stateFIPS":"18","case_count":0,"delta":0,"infect_prob":0},{"countyFIPS":"18049","pop":19974,"date":"2020-03-08","deaths":0,"County Name":"Fulton County","State":"IN","stateFIPS":"18","case_count":0,"delta":0,"infect_prob":0},{"countyFIPS":"18049","pop":19974,"date":"2020-03-09","deaths":0,"County Name":"Fulton County","State":"IN","stateFIPS":"18","case_count":0,"delta":0,"infect_prob":0},{"countyFIPS":"18049","pop":19974,"date":"2020-03-10","deaths":0,"County Name":"Fulton County","State":"IN","stateFIPS":"18","case_count":0,"delta":0,"infect_prob":0},{"countyFIPS":"18049","pop":19974,"date":"2020-03-11","deaths":0,"County Name":"Fulton County","State":"IN","stateFIPS":"18","case_count":0,"delta":0,"infect_prob":0},{"countyFIPS":"18049","pop":19974,"date":"2020-03-12","deaths":0,"County Name":"Fulton County","State":"IN","stateFIPS":"18","case_count":0,"delta":0,"infect_prob":0},{"countyFIPS":"18049","pop":19974,"date":"2020-03-13","deaths":0,"County Name":"Fulton County","State":"IN","stateFIPS":"18","case_count":0,"delta":0,"infect_prob":0},{"countyFIPS":"18049","pop":19974,"date":"2020-03-14","deaths":0,"County Name":"Fulton County","State":"IN","stateFIPS":"18","case_count":0,"delta":0,"infect_prob":0},{"countyFIPS":"18049","pop":19974,"date":"2020-03-15","deaths":0,"County Name":"Fulton County","State":"IN","stateFIPS":"18","case_count":0,"delta":0,"infect_prob":0},{"countyFIPS":"18049","pop":19974,"date":"2020-03-16","deaths":0,"County Name":"Fulton County","State":"IN","stateFIPS":"18","case_count":0,"delta":0,"infect_prob":0},{"countyFIPS":"18049","pop":19974,"date":"2020-03-17","deaths":0,"County Name":"Fulton County","State":"IN","stateFIPS":"18","case_count":0,"delta":0,"infect_prob":0},{"countyFIPS":"18049","pop":19974,"date":"2020-03-18","deaths":0,"County Name":"Fulton County","State":"IN","stateFIPS":"18","case_count":0,"delta":0,"infect_prob":0},{"countyFIPS":"18049","pop":19974,"date":"2020-03-19","deaths":0,"County Name":"Fulton County","State":"IN","stateFIPS":"18","case_count":0,"delta":0,"infect_prob":0},{"countyFIPS":"18049","pop":19974,"date":"2020-03-20","deaths":0,"County Name":"Fulton County","State":"IN","stateFIPS":"18","case_count":0,"delta":0,"infect_prob":0},{"countyFIPS":"18049","pop":19974,"date":"2020-03-21","deaths":0,"County Name":"Fulton County","State":"IN","stateFIPS":"18","case_count":0,"delta":0,"infect_prob":0},{"countyFIPS":"18049","pop":19974,"date":"2020-03-22","deaths":0,"County Name":"Fulton County","State":"IN","stateFIPS":"18","case_count":0,"delta":0,"infect_prob":0},{"countyFIPS":"18049","pop":19974,"date":"2020-03-23","deaths":0,"County Name":"Fulton County","State":"IN","stateFIPS":"18","case_count":0,"delta":0,"infect_prob":0},{"countyFIPS":"18049","pop":19974,"date":"2020-03-24","deaths":0,"County Name":"Fulton County","State":"IN","stateFIPS":"18","case_count":0,"delta":0,"infect_prob":0},{"countyFIPS":"18049","pop":19974,"date":"2020-03-25","deaths":0,"County Name":"Fulton County","State":"IN","stateFIPS":"18","case_count":0,"delta":0,"infect_prob":0},{"countyFIPS":"18049","pop":19974,"date":"2020-03-26","deaths":0,"County Name":"Fulton County","State":"IN","stateFIPS":"18","case_count":0,"delta":0,"infect_prob":0},{"countyFIPS":"18049","pop":19974,"date":"2020-03-27","deaths":0,"County Name":"Fulton County","State":"IN","stateFIPS":"18","case_count":0,"delta":0,"infect_prob":0},{"countyFIPS":"18049","pop":19974,"date":"2020-03-28","deaths":0,"County Name":"Fulton County","State":"IN","stateFIPS":"18","case_count":1,"delta":1,"r_t":41.9273,"infect_prob":0.0501,"doubling":1},{"countyFIPS":"18049","pop":19974,"date":"2020-03-29","deaths":0,"County Name":"Fulton County","State":"IN","stateFIPS":"18","case_count":1,"delta":0,"per_delta":0,"r_t":0,"infect_prob":0.0501,"doubling":2},{"countyFIPS":"18049","pop":19974,"date":"2020-03-30","deaths":0,"County Name":"Fulton County","State":"IN","stateFIPS":"18","case_count":1,"delta":0,"per_delta":0,"r_t":0,"infect_prob":0.0501,"r_t_three":13.9758,"doubling":3},{"countyFIPS":"18049","pop":19974,"date":"2020-03-31","deaths":0,"County Name":"Fulton County","State":"IN","stateFIPS":"18","case_count":1,"delta":0,"per_delta":0,"r_t":0,"infect_prob":0.0501,"r_t_three":0,"doubling":4},{"countyFIPS":"18049","pop":19974,"date":"2020-04-01","deaths":0,"County Name":"Fulton County","State":"IN","stateFIPS":"18","case_count":1,"delta":0,"per_delta":0,"r_t":0,"infect_prob":0.0501,"r_t_three":0,"doubling":5},{"countyFIPS":"18049","pop":19974,"date":"2020-04-02","deaths":0,"County Name":"Fulton County","State":"IN","stateFIPS":"18","case_count":1,"delta":0,"per_delta":0,"r_t":0,"infect_prob":0.0501,"r_t_three":0,"doubling":6},{"countyFIPS":"18049","pop":19974,"date":"2020-04-03","deaths":0,"County Name":"Fulton County","State":"IN","stateFIPS":"18","case_count":1,"delta":0,"per_delta":0,"r_t":0,"infect_prob":0.0501,"r_t_three":0,"r_t_seven":5.9896,"doubling":7},{"countyFIPS":"18049","pop":19974,"date":"2020-04-04","deaths":0,"County Name":"Fulton County","State":"IN","stateFIPS":"18","case_count":2,"delta":1,"per_delta":1,"r_t":9.8233,"infect_prob":0.1001,"r_t_three":3.2744,"r_t_seven":1.4033,"doubling":8},{"countyFIPS":"18049","pop":19974,"date":"2020-04-05","deaths":0,"County Name":"Fulton County","State":"IN","stateFIPS":"18","case_count":2,"delta":0,"per_delta":0,"r_t":0,"infect_prob":0.1001,"r_t_three":3.2744,"r_t_seven":1.4033,"doubling":9},{"countyFIPS":"18049","pop":19974,"date":"2020-04-06","deaths":0,"County Name":"Fulton County","State":"IN","stateFIPS":"18","case_count":3,"delta":1,"per_delta":0.5,"r_t":5.4829,"infect_prob":0.1001,"r_t_three":5.1021,"r_t_seven":2.1866,"doubling":3},{"countyFIPS":"18049","pop":19974,"date":"2020-04-07","deaths":0,"County Name":"Fulton County","State":"IN","stateFIPS":"18","case_count":3,"delta":0,"per_delta":0,"r_t":0,"infect_prob":0.1001,"r_t_three":1.8276,"r_t_seven":2.1866,"doubling":4},{"countyFIPS":"18049","pop":19974,"date":"2020-04-08","deaths":0,"County Name":"Fulton County","State":"IN","stateFIPS":"18","case_count":3,"delta":0,"per_delta":0,"r_t":0,"infect_prob":0.1001,"r_t_three":1.8276,"r_t_seven":2.1866,"doubling":5},{"countyFIPS":"18049","pop":19974,"date":"2020-04-09","deaths":0,"County Name":"Fulton County","State":"IN","stateFIPS":"18","case_count":3,"delta":0,"per_delta":0,"r_t":0,"infect_prob":0.1001,"r_t_three":0,"r_t_seven":2.1866,"doubling":6},{"countyFIPS":"18049","pop":19974,"date":"2020-04-10","deaths":0,"County Name":"Fulton County","State":"IN","stateFIPS":"18","case_count":3,"delta":0,"per_delta":0,"r_t":0,"infect_prob":0.1001,"r_t_three":0,"r_t_seven":2.1866,"doubling":7},{"countyFIPS":"18049","pop":19974,"date":"2020-04-11","deaths":0,"County Name":"Fulton County","State":"IN","stateFIPS":"18","case_count":3,"delta":0,"per_delta":0,"r_t":0,"infect_prob":0.1001,"r_t_three":0,"r_t_seven":0.7833,"doubling":8},{"countyFIPS":"18049","pop":19974,"date":"2020-04-12","deaths":0,"County Name":"Fulton County","State":"IN","stateFIPS":"18","case_count":3,"delta":0,"per_delta":0,"r_t":0,"infect_prob":0.1001,"r_t_three":0,"r_t_seven":0.7833,"doubling":9},{"countyFIPS":"18049","pop":19974,"date":"2020-04-13","deaths":0,"County Name":"Fulton County","State":"IN","stateFIPS":"18","case_count":3,"delta":0,"per_delta":0,"r_t":0,"infect_prob":0.0501,"r_t_three":0,"r_t_seven":0,"doubling":10},{"countyFIPS":"18049","pop":19974,"date":"2020-04-14","deaths":0,"County Name":"Fulton County","State":"IN","stateFIPS":"18","case_count":3,"delta":0,"per_delta":0,"r_t":0,"infect_prob":0.0501,"r_t_three":0,"r_t_seven":0,"doubling":11},{"countyFIPS":"18049","pop":19974,"date":"2020-04-15","deaths":0,"County Name":"Fulton County","State":"IN","stateFIPS":"18","case_count":3,"delta":0,"per_delta":0,"r_t":0,"infect_prob":0,"r_t_three":0,"r_t_seven":0,"doubling":12},{"countyFIPS":"18049","pop":19974,"date":"2020-04-16","deaths":0,"County Name":"Fulton County","State":"IN","stateFIPS":"18","case_count":3,"delta":0,"per_delta":0,"r_t":0,"infect_prob":0,"r_t_three":0,"r_t_seven":0,"doubling":13},{"countyFIPS":"18049","pop":19974,"date":"2020-04-17","deaths":0,"County Name":"Fulton County","State":"IN","stateFIPS":"18","case_count":4,"delta":1,"per_delta":0.3333,"r_t":33.3029,"infect_prob":0.0501,"r_t_three":11.101,"r_t_seven":4.7576,"doubling":14},{"countyFIPS":"18049","pop":19974,"date":"2020-04-18","deaths":0,"County Name":"Fulton County","State":"IN","stateFIPS":"18","case_count":5,"delta":1,"per_delta":0.25,"r_t":9.2976,"infect_prob":0.1001,"r_t_three":14.2001,"r_t_seven":6.0858,"doubling":13},{"countyFIPS":"18049","pop":19974,"date":"2020-04-19","deaths":0,"County Name":"Fulton County","State":"IN","stateFIPS":"18","case_count":6,"delta":1,"per_delta":0.2,"r_t":4.1898,"infect_prob":0.1502,"r_t_three":15.5967,"r_t_seven":6.6843,"doubling":14},{"countyFIPS":"18049","pop":19974,"date":"2020-04-20","deaths":0,"County Name":"Fulton County","State":"IN","stateFIPS":"18","case_count":6,"delta":0,"per_delta":0,"r_t":0,"infect_prob":0.1502,"r_t_three":4.4958,"r_t_seven":6.6843,"doubling":15},{"countyFIPS":"18049","pop":19974,"date":"2020-04-21","deaths":0,"County Name":"Fulton County","State":"IN","stateFIPS":"18","case_count":6,"delta":0,"per_delta":0,"r_t":0,"infect_prob":0.1502,"r_t_three":1.3966,"r_t_seven":6.6843,"doubling":16},{"countyFIPS":"18049","pop":19974,"date":"2020-04-22","deaths":0,"County Name":"Fulton County","State":"IN","stateFIPS":"18","case_count":6,"delta":0,"per_delta":0,"r_t":0,"infect_prob":0.1502,"r_t_three":0,"r_t_seven":6.6843,"doubling":17},{"countyFIPS":"18049","pop":19974,"date":"2020-04-23","deaths":0,"County Name":"Fulton County","State":"IN","stateFIPS":"18","case_count":6,"delta":0,"per_delta":0,"r_t":0,"infect_prob":0.1502,"r_t_three":0,"r_t_seven":6.6843,"doubling":18},{"countyFIPS":"18049","pop":19974,"date":"2020-04-24","deaths":0,"County Name":"Fulton County","State":"IN","stateFIPS":"18","case_count":7,"delta":1,"per_delta":0.1667,"r_t":2.761,"infect_prob":0.2003,"r_t_three":0.9203,"r_t_seven":2.3212,"doubling":8},{"countyFIPS":"18049","pop":19974,"date":"2020-04-25","deaths":0,"County Name":"Fulton County","State":"IN","stateFIPS":"18","case_count":10,"delta":3,"per_delta":0.4286,"r_t":7.6516,"infect_prob":0.3505,"r_t_three":3.4709,"r_t_seven":2.0861,"doubling":8},{"countyFIPS":"18049","pop":19974,"date":"2020-04-26","deaths":0,"County Name":"Fulton County","State":"IN","stateFIPS":"18","case_count":13,"delta":3,"per_delta":0.3,"r_t":5.0025,"infect_prob":0.4506,"r_t_three":5.1384,"r_t_seven":2.2022,"doubling":3},{"countyFIPS":"18049","pop":19974,"date":"2020-04-27","deaths":0,"County Name":"Fulton County","State":"IN","stateFIPS":"18","case_count":23,"delta":10,"per_delta":0.7692,"r_t":8.8539,"infect_prob":0.9012,"r_t_three":7.1693,"r_t_seven":3.467,"doubling":2},{"countyFIPS":"18049","pop":19974,"date":"2020-04-28","deaths":0,"County Name":"Fulton County","State":"IN","stateFIPS":"18","case_count":26,"delta":3,"per_delta":0.1304,"r_t":1.5136,"infect_prob":1.0013,"r_t_three":5.1233,"r_t_seven":3.6832,"doubling":3},{"countyFIPS":"18049","pop":19974,"date":"2020-04-29","deaths":0,"County Name":"Fulton County","State":"IN","stateFIPS":"18","case_count":26,"delta":0,"per_delta":0,"r_t":0,"infect_prob":1.0013,"r_t_three":3.4558,"r_t_seven":3.6832,"doubling":4},{"countyFIPS":"18049","pop":19974,"date":"2020-04-30","deaths":1,"County Name":"Fulton County","State":"IN","stateFIPS":"18","case_count":27,"delta":1,"per_delta":0.0385,"r_t":0.3214,"infect_prob":1.0514,"r_t_three":0.6117,"r_t_seven":3.7291,"doubling":4},{"countyFIPS":"18049","pop":19974,"date":"2020-05-01","deaths":1,"County Name":"Fulton County","State":"IN","stateFIPS":"18","case_count":30,"delta":3,"per_delta":0.1111,"r_t":0.9472,"infect_prob":1.2016,"r_t_three":0.4229,"r_t_seven":3.47,"doubling":5},{"countyFIPS":"18049","pop":19974,"date":"2020-05-02","deaths":1,"County Name":"Fulton County","State":"IN","stateFIPS":"18","case_count":31,"delta":1,"per_delta":0.0333,"r_t":0.3344,"infect_prob":1.2516,"r_t_three":0.5343,"r_t_seven":2.4247,"doubling":6},{"countyFIPS":"18049","pop":19974,"date":"2020-05-03","deaths":1,"County Name":"Fulton County","State":"IN","stateFIPS":"18","case_count":33,"delta":2,"per_delta":0.0645,"r_t":0.7493,"infect_prob":1.3017,"r_t_three":0.677,"r_t_seven":1.8171,"doubling":7},{"countyFIPS":"18049","pop":19974,"date":"2020-05-04","deaths":1,"County Name":"Fulton County","State":"IN","stateFIPS":"18","case_count":33,"delta":0,"per_delta":0,"r_t":0,"infect_prob":1.1515,"r_t_three":0.3612,"r_t_seven":0.5523,"doubling":8},{"countyFIPS":"18049","pop":19974,"date":"2020-05-05","deaths":1,"County Name":"Fulton County","State":"IN","stateFIPS":"18","case_count":34,"delta":1,"per_delta":0.0303,"r_t":0.5187,"infect_prob":1.0514,"r_t_three":0.4226,"r_t_seven":0.4101,"doubling":9},{"countyFIPS":"18049","pop":19974,"date":"2020-05-06","deaths":1,"County Name":"Fulton County","State":"IN","stateFIPS":"18","case_count":34,"delta":0,"per_delta":0,"r_t":0,"infect_prob":0.5507,"r_t_three":0.1729,"r_t_seven":0.4101,"doubling":10},{"countyFIPS":"18049","pop":19974,"date":"2020-05-07","deaths":1,"County Name":"Fulton County","State":"IN","stateFIPS":"18","case_count":34,"delta":0,"per_delta":0,"r_t":0,"infect_prob":0.4005,"r_t_three":0.1729,"r_t_seven":0.3642,"doubling":11},{"countyFIPS":"18049","pop":19974,"date":"2020-05-08","deaths":1,"County Name":"Fulton County","State":"IN","stateFIPS":"18","case_count":34,"delta":0,"per_delta":0,"r_t":0,"infect_prob":0.4005,"r_t_three":0,"r_t_seven":0.2289,"doubling":12},{"countyFIPS":"18049","pop":19974,"date":"2020-05-09","deaths":1,"County Name":"Fulton County","State":"IN","stateFIPS":"18","case_count":36,"delta":2,"per_delta":0.0588,"r_t":2.7465,"infect_prob":0.4506,"r_t_three":0.9155,"r_t_seven":0.5735,"doubling":13},{"countyFIPS":"18049","pop":19974,"date":"2020-05-10","deaths":1,"County Name":"Fulton County","State":"IN","stateFIPS":"18","case_count":36,"delta":0,"per_delta":0,"r_t":0,"infect_prob":0.3004,"r_t_three":0.9155,"r_t_seven":0.4665,"doubling":14},{"countyFIPS":"18049","pop":19974,"date":"2020-05-11","deaths":1,"County Name":"Fulton County","State":"IN","stateFIPS":"18","case_count":36,"delta":0,"per_delta":0,"r_t":0,"infect_prob":0.2503,"r_t_three":0.9155,"r_t_seven":0.4665,"doubling":15},{"countyFIPS":"18049","pop":19974,"date":"2020-05-12","deaths":1,"County Name":"Fulton County","State":"IN","stateFIPS":"18","case_count":37,"delta":1,"per_delta":0.0278,"r_t":1.9547,"infect_prob":0.2003,"r_t_three":0.6516,"r_t_seven":0.6716,"doubling":16},{"countyFIPS":"18049","pop":19974,"date":"2020-05-13","deaths":1,"County Name":"Fulton County","State":"IN","stateFIPS":"18","case_count":37,"delta":0,"per_delta":0,"r_t":0,"infect_prob":0.2003,"r_t_three":0.6516,"r_t_seven":0.6716,"doubling":17},{"countyFIPS":"18049","pop":19974,"date":"2020-05-14","deaths":1,"County Name":"Fulton County","State":"IN","stateFIPS":"18","case_count":39,"delta":2,"per_delta":0.0541,"r_t":3.882,"infect_prob":0.2503,"r_t_three":1.9455,"r_t_seven":1.2262,"doubling":18},{"countyFIPS":"18049","pop":19974,"date":"2020-05-15","deaths":1,"County Name":"Fulton County","State":"IN","stateFIPS":"18","case_count":39,"delta":0,"per_delta":0,"r_t":0,"infect_prob":0.2503,"r_t_three":1.294,"r_t_seven":1.2262,"doubling":19},{"countyFIPS":"18049","pop":19974,"date":"2020-05-16","deaths":1,"County Name":"Fulton County","State":"IN","stateFIPS":"18","case_count":42,"delta":3,"per_delta":0.0769,"r_t":4.5014,"infect_prob":0.4005,"r_t_three":2.7945,"r_t_seven":1.4769,"doubling":20},{"countyFIPS":"18049","pop":19974,"date":"2020-05-17","deaths":1,"County Name":"Fulton County","State":"IN","stateFIPS":"18","case_count":43,"delta":1,"per_delta":0.0238,"r_t":1.1931,"infect_prob":0.4506,"r_t_three":1.8981,"r_t_seven":1.6473,"doubling":21},{"countyFIPS":"18049","pop":19974,"date":"2020-05-18","deaths":1,"County Name":"Fulton County","State":"IN","stateFIPS":"18","case_count":44,"delta":1,"per_delta":0.0233,"r_t":0.9978,"infect_prob":0.4005,"r_t_three":2.2308,"r_t_seven":1.7898,"doubling":22},{"countyFIPS":"18049","pop":19974,"date":"2020-05-19","deaths":1,"County Name":"Fulton County","State":"IN","stateFIPS":"18","case_count":45,"delta":1,"per_delta":0.0227,"r_t":0.8903,"infect_prob":0.4506,"r_t_three":1.0271,"r_t_seven":1.6378,"doubling":23},{"countyFIPS":"18049","pop":19974,"date":"2020-05-20","deaths":1,"County Name":"Fulton County","State":"IN","stateFIPS":"18","case_count":46,"delta":1,"per_delta":0.0222,"r_t":0.8434,"infect_prob":0.5007,"r_t_three":0.9105,"r_t_seven":1.7583,"doubling":24},{"countyFIPS":"18049","pop":19974,"date":"2020-05-21","deaths":1,"County Name":"Fulton County","State":"IN","stateFIPS":"18","case_count":46,"delta":0,"per_delta":0,"r_t":0,"infect_prob":0.4506,"r_t_three":0.5779,"r_t_seven":1.2037,"doubling":25},{"countyFIPS":"18049","pop":19974,"date":"2020-05-22","deaths":1,"County Name":"Fulton County","State":"IN","stateFIPS":"18","case_count":46,"delta":0,"per_delta":0,"r_t":0,"infect_prob":0.4506,"r_t_three":0.2811,"r_t_seven":1.2037,"doubling":26},{"countyFIPS":"18049","pop":19974,"date":"2020-05-23","deaths":1,"County Name":"Fulton County","State":"IN","stateFIPS":"18","case_count":46,"delta":0,"per_delta":0,"r_t":0,"infect_prob":0.3505,"r_t_three":0,"r_t_seven":0.5607,"doubling":27},{"countyFIPS":"18049","pop":19974,"date":"2020-05-24","deaths":1,"County Name":"Fulton County","State":"IN","stateFIPS":"18","case_count":46,"delta":0,"per_delta":0,"r_t":0,"infect_prob":0.3505,"r_t_three":0,"r_t_seven":0.3902,"doubling":28},{"countyFIPS":"18049","pop":19974,"date":"2020-05-25","deaths":1,"County Name":"Fulton County","State":"IN","stateFIPS":"18","case_count":47,"delta":1,"per_delta":0.0217,"r_t":2.004,"infect_prob":0.2503,"r_t_three":0.668,"r_t_seven":0.534,"doubling":28},{"countyFIPS":"18049","pop":19974,"date":"2020-05-26","deaths":1,"County Name":"Fulton County","State":"IN","stateFIPS":"18","case_count":47,"delta":0,"per_delta":0,"r_t":0,"infect_prob":0.2003,"r_t_three":0.668,"r_t_seven":0.4068,"doubling":29},{"countyFIPS":"18049","pop":19974,"date":"2020-05-27","deaths":1,"County Name":"Fulton County","State":"IN","stateFIPS":"18","case_count":47,"delta":0,"per_delta":0,"r_t":0,"infect_prob":0.1502,"r_t_three":0.668,"r_t_seven":0.2863,"doubling":30},{"countyFIPS":"18049","pop":19974,"date":"2020-05-28","deaths":1,"County Name":"Fulton County","State":"IN","stateFIPS":"18","case_count":47,"delta":0,"per_delta":0,"r_t":0,"infect_prob":0.1001,"r_t_three":0,"r_t_seven":0.2863,"doubling":31},{"countyFIPS":"18049","pop":19974,"date":"2020-05-29","deaths":1,"County Name":"Fulton County","State":"IN","stateFIPS":"18","case_count":48,"delta":1,"per_delta":0.0213,"r_t":4.1927,"infect_prob":0.1001,"r_t_three":1.3976,"r_t_seven":0.8852,"doubling":32},{"countyFIPS":"18049","pop":19974,"date":"2020-05-30","deaths":1,"County Name":"Fulton County","State":"IN","stateFIPS":"18","case_count":48,"delta":0,"per_delta":0,"r_t":0,"infect_prob":0.1001,"r_t_three":1.3976,"r_t_seven":0.8852,"doubling":33},{"countyFIPS":"18049","pop":19974,"date":"2020-05-31","deaths":1,"County Name":"Fulton County","State":"IN","stateFIPS":"18","case_count":49,"delta":1,"per_delta":0.0208,"r_t":3.586,"infect_prob":0.1502,"r_t_three":2.5929,"r_t_seven":1.3975,"doubling":34},{"countyFIPS":"18049","pop":19974,"date":"2020-06-01","deaths":1,"County Name":"Fulton County","State":"IN","stateFIPS":"18","case_count":49,"delta":0,"per_delta":0,"r_t":0,"infect_prob":0.1502,"r_t_three":1.1953,"r_t_seven":1.1112,"doubling":35},{"countyFIPS":"18049","pop":19974,"date":"2020-06-02","deaths":1,"County Name":"Fulton County","State":"IN","stateFIPS":"18","case_count":49,"delta":0,"per_delta":0,"r_t":0,"infect_prob":0.1502,"r_t_three":1.1953,"r_t_seven":1.1112,"doubling":36},{"countyFIPS":"18049","pop":19974,"date":"2020-06-03","deaths":1,"County Name":"Fulton County","State":"IN","stateFIPS":"18","case_count":50,"delta":1,"per_delta":0.0204,"r_t":2.7808,"infect_prob":0.1502,"r_t_three":0.9269,"r_t_seven":1.5085,"doubling":37},{"countyFIPS":"18049","pop":19974,"date":"2020-06-04","deaths":1,"County Name":"Fulton County","State":"IN","stateFIPS":"18","case_count":50,"delta":0,"per_delta":0,"r_t":0,"infect_prob":0.1502,"r_t_three":0.9269,"r_t_seven":1.5085,"doubling":38},{"countyFIPS":"18049","pop":19974,"date":"2020-06-05","deaths":1,"County Name":"Fulton County","State":"IN","stateFIPS":"18","case_count":51,"delta":1,"per_delta":0.02,"r_t":2.5862,"infect_prob":0.2003,"r_t_three":1.789,"r_t_seven":1.279,"doubling":39},{"countyFIPS":"18049","pop":19974,"date":"2020-06-06","deaths":1,"County Name":"Fulton County","State":"IN","stateFIPS":"18","case_count":51,"delta":0,"per_delta":0,"r_t":0,"infect_prob":0.2003,"r_t_three":0.8621,"r_t_seven":1.279,"doubling":40},{"countyFIPS":"18049","pop":19974,"date":"2020-06-07","deaths":1,"County Name":"Fulton County","State":"IN","stateFIPS":"18","case_count":51,"delta":0,"per_delta":0,"r_t":0,"infect_prob":0.1502,"r_t_three":0.8621,"r_t_seven":0.7667,"doubling":41},{"countyFIPS":"18049","pop":19974,"date":"2020-06-08","deaths":1,"County Name":"Fulton County","State":"IN","stateFIPS":"18","case_count":51,"delta":0,"per_delta":0,"r_t":0,"infect_prob":0.1502,"r_t_three":0,"r_t_seven":0.7667,"doubling":42},{"countyFIPS":"18049","pop":19974,"date":"2020-06-09","deaths":1,"County Name":"Fulton County","State":"IN","stateFIPS":"18","case_count":51,"delta":0,"per_delta":0,"r_t":0,"infect_prob":0.1001,"r_t_three":0,"r_t_seven":0.7667,"doubling":43},{"countyFIPS":"18049","pop":19974,"date":"2020-06-10","deaths":1,"County Name":"Fulton County","State":"IN","stateFIPS":"18","case_count":51,"delta":0,"per_delta":0,"r_t":0,"infect_prob":0.1001,"r_t_three":0,"r_t_seven":0.3695,"doubling":44},{"countyFIPS":"18049","pop":19974,"date":"2020-06-11","deaths":1,"County Name":"Fulton County","State":"IN","stateFIPS":"18","case_count":52,"delta":1,"per_delta":0.0196,"r_t":5.2292,"infect_prob":0.1502,"r_t_three":1.7431,"r_t_seven":1.1165,"doubling":45},{"countyFIPS":"18049","pop":19974,"date":"2020-06-12","deaths":1,"County Name":"Fulton County","State":"IN","stateFIPS":"18","case_count":53,"delta":1,"per_delta":0.0192,"r_t":4.7309,"infect_prob":0.1502,"r_t_three":3.32,"r_t_seven":1.4229,"doubling":44},{"countyFIPS":"18049","pop":19974,"date":"2020-06-13","deaths":1,"County Name":"Fulton County","State":"IN","stateFIPS":"18","case_count":53,"delta":0,"per_delta":0,"r_t":0,"infect_prob":0.1502,"r_t_three":3.32,"r_t_seven":1.4229,"doubling":45},{"countyFIPS":"18049","pop":19974,"date":"2020-06-14","deaths":1,"County Name":"Fulton County","State":"IN","stateFIPS":"18","case_count":55,"delta":2,"per_delta":0.0377,"r_t":5.3366,"infect_prob":0.2003,"r_t_three":3.3558,"r_t_seven":2.1852,"doubling":45},{"countyFIPS":"18049","pop":19974,"date":"2020-06-15","deaths":1,"County Name":"Fulton County","State":"IN","stateFIPS":"18","case_count":55,"delta":0,"per_delta":0,"r_t":0,"infect_prob":0.2003,"r_t_three":1.7789,"r_t_seven":2.1852,"doubling":46},{"countyFIPS":"18049","pop":19974,"date":"2020-06-16","deaths":1,"County Name":"Fulton County","State":"IN","stateFIPS":"18","case_count":56,"delta":1,"per_delta":0.0182,"r_t":1.6435,"infect_prob":0.2503,"r_t_three":2.3267,"r_t_seven":2.42,"doubling":47},{"countyFIPS":"18049","pop":19974,"date":"2020-06-17","deaths":1,"County Name":"Fulton County","State":"IN","stateFIPS":"18","case_count":56,"delta":0,"per_delta":0,"r_t":0,"infect_prob":0.2503,"r_t_three":0.5478,"r_t_seven":2.42,"doubling":48},{"countyFIPS":"18049","pop":19974,"date":"2020-06-18","deaths":1,"County Name":"Fulton County","State":"IN","stateFIPS":"18","case_count":58,"delta":2,"per_delta":0.0357,"r_t":2.835,"infect_prob":0.3505,"r_t_three":1.4928,"r_t_seven":2.078,"doubling":49},{"countyFIPS":"18049","pop":19974,"date":"2020-06-19","deaths":1,"County Name":"Fulton County","State":"IN","stateFIPS":"18","case_count":60,"delta":2,"per_delta":0.0345,"r_t":2.5236,"infect_prob":0.4506,"r_t_three":1.7862,"r_t_seven":1.7627,"doubling":50},{"countyFIPS":"18049","pop":19974,"date":"2020-06-20","deaths":1,"County Name":"Fulton County","State":"IN","stateFIPS":"18","case_count":61,"delta":1,"per_delta":0.0167,"r_t":1.0881,"infect_prob":0.4506,"r_t_three":2.1489,"r_t_seven":1.9181,"doubling":50},{"countyFIPS":"18049","pop":19974,"date":"2020-06-21","deaths":1,"County Name":"Fulton County","State":"IN","stateFIPS":"18","case_count":62,"delta":1,"per_delta":0.0164,"r_t":0.964,"infect_prob":0.4506,"r_t_three":1.5252,"r_t_seven":1.2935,"doubling":51},{"countyFIPS":"18049","pop":19974,"date":"2020-06-22","deaths":1,"County Name":"Fulton County","State":"IN","stateFIPS":"18","case_count":62,"delta":0,"per_delta":0,"r_t":0,"infect_prob":0.4506,"r_t_three":0.684,"r_t_seven":1.2935,"doubling":52},{"countyFIPS":"18049","pop":19974,"date":"2020-06-23","deaths":1,"County Name":"Fulton County","State":"IN","stateFIPS":"18","case_count":63,"delta":1,"per_delta":0.0161,"r_t":0.9235,"infect_prob":0.4005,"r_t_three":0.6292,"r_t_seven":1.1906,"doubling":52},{"countyFIPS":"18049","pop":19974,"date":"2020-06-24","deaths":1,"County Name":"Fulton County","State":"IN","stateFIPS":"18","case_count":64,"delta":1,"per_delta":0.0159,"r_t":0.9702,"infect_prob":0.4506,"r_t_three":0.6312,"r_t_seven":1.3292,"doubling":53},{"countyFIPS":"18049","pop":19974,"date":"2020-06-25","deaths":1,"County Name":"Fulton County","State":"IN","stateFIPS":"18","case_count":64,"delta":0,"per_delta":0,"r_t":0,"infect_prob":0.4005,"r_t_three":0.6312,"r_t_seven":0.9242,"doubling":54},{"countyFIPS":"18049","pop":19974,"date":"2020-06-26","deaths":1,"County Name":"Fulton County","State":"IN","stateFIPS":"18","case_count":64,"delta":0,"per_delta":0,"r_t":0,"infect_prob":0.4005,"r_t_three":0.3234,"r_t_seven":0.5637,"doubling":55},{"countyFIPS":"18049","pop":19974,"date":"2020-06-27","deaths":1,"County Name":"Fulton County","State":"IN","stateFIPS":"18","case_count":65,"delta":1,"per_delta":0.0156,"r_t":1.4317,"infect_prob":0.3505,"r_t_three":0.4772,"r_t_seven":0.6128,"doubling":56},{"countyFIPS":"18049","pop":19974,"date":"2020-06-28","deaths":1,"County Name":"Fulton County","State":"IN","stateFIPS":"18","case_count":65,"delta":0,"per_delta":0,"r_t":0,"infect_prob":0.2503,"r_t_three":0.4772,"r_t_seven":0.4751,"doubling":57},{"countyFIPS":"18049","pop":19974,"date":"2020-06-29","deaths":1,"County Name":"Fulton County","State":"IN","stateFIPS":"18","case_count":65,"delta":0,"per_delta":0,"r_t":0,"infect_prob":0.2003,"r_t_three":0.4772,"r_t_seven":0.4751,"doubling":58},{"countyFIPS":"18049","pop":19974,"date":"2020-06-30","deaths":1,"County Name":"Fulton County","State":"IN","stateFIPS":"18","case_count":66,"delta":1,"per_delta":0.0154,"r_t":2.3143,"infect_prob":0.2003,"r_t_three":0.7714,"r_t_seven":0.6737,"doubling":59},{"countyFIPS":"18049","pop":19974,"date":"2020-07-01","deaths":1,"County Name":"Fulton County","State":"IN","stateFIPS":"18","case_count":66,"delta":0,"per_delta":0,"r_t":0,"infect_prob":0.2003,"r_t_three":0.7714,"r_t_seven":0.5351,"doubling":60},{"countyFIPS":"18049","pop":19974,"date":"2020-07-02","deaths":1,"County Name":"Fulton County","State":"IN","stateFIPS":"18","case_count":66,"delta":0,"per_delta":0,"r_t":0,"infect_prob":0.1502,"r_t_three":0.7714,"r_t_seven":0.5351,"doubling":61},{"countyFIPS":"18049","pop":19974,"date":"2020-07-03","deaths":1,"County Name":"Fulton County","State":"IN","stateFIPS":"18","case_count":68,"delta":2,"per_delta":0.0303,"r_t":5.4638,"infect_prob":0.2003,"r_t_three":1.8213,"r_t_seven":1.3157,"doubling":60},{"countyFIPS":"18049","pop":19974,"date":"2020-07-04","deaths":1,"County Name":"Fulton County","State":"IN","stateFIPS":"18","case_count":69,"delta":1,"per_delta":0.0147,"r_t":2.2222,"infect_prob":0.2503,"r_t_three":2.562,"r_t_seven":1.4286,"doubling":57},{"countyFIPS":"18049","pop":19974,"date":"2020-07-05","deaths":1,"County Name":"Fulton County","State":"IN","stateFIPS":"18","case_count":69,"delta":0,"per_delta":0,"r_t":0,"infect_prob":0.2503,"r_t_three":2.562,"r_t_seven":1.4286,"doubling":58},{"countyFIPS":"18049","pop":19974,"date":"2020-07-06","deaths":1,"County Name":"Fulton County","State":"IN","stateFIPS":"18","case_count":71,"delta":2,"per_delta":0.029,"r_t":3.084,"infect_prob":0.3004,"r_t_three":1.7687,"r_t_seven":1.8692,"doubling":59},{"countyFIPS":"18049","pop":19974,"date":"2020-07-07","deaths":1,"County Name":"Fulton County","State":"IN","stateFIPS":"18","case_count":71,"delta":0,"per_delta":0,"r_t":0,"infect_prob":0.3004,"r_t_three":1.028,"r_t_seven":1.5386,"doubling":60},{"countyFIPS":"18049","pop":19974,"date":"2020-07-08","deaths":1,"County Name":"Fulton County","State":"IN","stateFIPS":"18","case_count":72,"delta":1,"per_delta":0.0141,"r_t":1.2464,"infect_prob":0.3505,"r_t_three":1.4435,"r_t_seven":1.7166,"doubling":61},{"countyFIPS":"18049","pop":19974,"date":"2020-07-09","deaths":1,"County Name":"Fulton County","State":"IN","stateFIPS":"18","case_count":72,"delta":0,"per_delta":0,"r_t":0,"infect_prob":0.3004,"r_t_three":0.4155,"r_t_seven":1.7166,"doubling":62},{"countyFIPS":"18049","pop":19974,"date":"2020-07-10","deaths":1,"County Name":"Fulton County","State":"IN","stateFIPS":"18","case_count":72,"delta":0,"per_delta":0,"r_t":0,"infect_prob":0.3004,"r_t_three":0.4155,"r_t_seven":0.9361,"doubling":63},{"countyFIPS":"18049","pop":19974,"date":"2020-07-11","deaths":1,"County Name":"Fulton County","State":"IN","stateFIPS":"18","case_count":73,"delta":1,"per_delta":0.0139,"r_t":1.5177,"infect_prob":0.3505,"r_t_three":0.5059,"r_t_seven":0.8354,"doubling":61},{"countyFIPS":"18049","pop":19974,"date":"2020-07-12","deaths":1,"County Name":"Fulton County","State":"IN","stateFIPS":"18","case_count":73,"delta":0,"per_delta":0,"r_t":0,"infect_prob":0.2503,"r_t_three":0.5059,"r_t_seven":0.8354,"doubling":62},{"countyFIPS":"18049","pop":19974,"date":"2020-07-13","deaths":1,"County Name":"Fulton County","State":"IN","stateFIPS":"18","case_count":76,"delta":3,"per_delta":0.0411,"r_t":5.3707,"infect_prob":0.3505,"r_t_three":2.2961,"r_t_seven":1.1621,"doubling":61},{"countyFIPS":"18049","pop":19974,"date":"2020-07-14","deaths":1,"County Name":"Fulton County","State":"IN","stateFIPS":"18","case_count":79,"delta":3,"per_delta":0.0395,"r_t":4.2197,"infect_prob":0.5007,"r_t_three":3.1968,"r_t_seven":1.7649,"doubling":60},{"countyFIPS":"18049","pop":19974,"date":"2020-07-15","deaths":1,"County Name":"Fulton County","State":"IN","stateFIPS":"18","case_count":81,"delta":2,"per_delta":0.0253,"r_t":2.0089,"infect_prob":0.5007,"r_t_three":3.8664,"r_t_seven":1.8738,"doubling":61},{"countyFIPS":"18049","pop":19974,"date":"2020-07-16","deaths":1,"County Name":"Fulton County","State":"IN","stateFIPS":"18","case_count":83,"delta":2,"per_delta":0.0247,"r_t":1.5152,"infect_prob":0.6008,"r_t_three":2.5812,"r_t_seven":2.0903,"doubling":62},{"countyFIPS":"18049","pop":19974,"date":"2020-07-17","deaths":1,"County Name":"Fulton County","State":"IN","stateFIPS":"18","case_count":84,"delta":1,"per_delta":0.012,"r_t":0.6285,"infect_prob":0.6008,"r_t_three":1.3842,"r_t_seven":2.1801,"doubling":63},{"countyFIPS":"18049","pop":19974,"date":"2020-07-18","deaths":1,"County Name":"Fulton County","State":"IN","stateFIPS":"18","case_count":86,"delta":2,"per_delta":0.0238,"r_t":1.14,"infect_prob":0.7009,"r_t_three":1.0945,"r_t_seven":2.1261,"doubling":63},{"countyFIPS":"18049","pop":19974,"date":"2020-07-19","deaths":1,"County Name":"Fulton County","State":"IN","stateFIPS":"18","case_count":89,"delta":3,"per_delta":0.0349,"r_t":1.612,"infect_prob":0.8511,"r_t_three":1.1268,"r_t_seven":2.3564,"doubling":62},{"countyFIPS":"18049","pop":19974,"date":"2020-07-20","deaths":1,"County Name":"Fulton County","State":"IN","stateFIPS":"18","case_count":91,"delta":2,"per_delta":0.0225,"r_t":1.026,"infect_prob":0.9012,"r_t_three":1.2593,"r_t_seven":1.7357,"doubling":62},{"countyFIPS":"18049","pop":19974,"date":"2020-07-21","deaths":1,"County Name":"Fulton County","State":"IN","stateFIPS":"18","case_count":99,"delta":8,"per_delta":0.0879,"r_t":3.7135,"infect_prob":1.3017,"r_t_three":2.1172,"r_t_seven":1.6634,"doubling":49},{"countyFIPS":"18049","pop":19974,"date":"2020-07-22","deaths":1,"County Name":"Fulton County","State":"IN","stateFIPS":"18","case_count":100,"delta":1,"per_delta":0.0101,"r_t":0.3973,"infect_prob":1.2016,"r_t_three":1.7122,"r_t_seven":1.4332,"doubling":50},{"countyFIPS":"18049","pop":19974,"date":"2020-07-23","deaths":1,"County Name":"Fulton County","State":"IN","stateFIPS":"18","case_count":102,"delta":2,"per_delta":0.02,"r_t":0.7167,"infect_prob":1.1515,"r_t_three":1.6091,"r_t_seven":1.3191,"doubling":49},{"countyFIPS":"18049","pop":19974,"date":"2020-07-24","deaths":1,"County Name":"Fulton County","State":"IN","stateFIPS":"18","case_count":105,"delta":3,"per_delta":0.0294,"r_t":1.0171,"infect_prob":1.2016,"r_t_three":0.7103,"r_t_seven":1.3746,"doubling":43},{"countyFIPS":"18049","pop":19974,"date":"2020-07-25","deaths":1,"County Name":"Fulton County","State":"IN","stateFIPS":"18","case_count":108,"delta":3,"per_delta":0.0286,"r_t":0.9959,"infect_prob":1.2516,"r_t_three":0.9099,"r_t_seven":1.3541,"doubling":42},{"countyFIPS":"18049","pop":19974,"date":"2020-07-26","deaths":1,"County Name":"Fulton County","State":"IN","stateFIPS":"18","case_count":109,"delta":1,"per_delta":0.0093,"r_t":0.338,"infect_prob":1.2516,"r_t_three":0.7837,"r_t_seven":1.1721,"doubling":43},{"countyFIPS":"18049","pop":19974,"date":"2020-07-27","deaths":1,"County Name":"Fulton County","State":"IN","stateFIPS":"18","case_count":119,"delta":10,"per_delta":0.0917,"r_t":3.3603,"infect_prob":1.6521,"r_t_three":1.5647,"r_t_seven":1.5055,"doubling":39},{"countyFIPS":"18049","pop":19974,"date":"2020-07-28","deaths":1,"County Name":"Fulton County","State":"IN","stateFIPS":"18","case_count":122,"delta":3,"per_delta":0.0252,"r_t":0.9242,"infect_prob":1.6521,"r_t_three":1.5408,"r_t_seven":1.1071,"doubling":39},{"countyFIPS":"18049","pop":19974,"date":"2020-07-29","deaths":1,"County Name":"Fulton County","State":"IN","stateFIPS":"18","case_count":125,"delta":3,"per_delta":0.0246,"r_t":0.8487,"infect_prob":1.7022,"r_t_three":1.7111,"r_t_seven":1.1716,"doubling":37},{"countyFIPS":"18049","pop":19974,"date":"2020-07-30","deaths":1,"County Name":"Fulton County","State":"IN","stateFIPS":"18","case_count":130,"delta":5,"per_delta":0.04,"r_t":1.3176,"infect_prob":1.552,"r_t_three":1.0302,"r_t_seven":1.2574,"doubling":34},{"countyFIPS":"18049","pop":19974,"date":"2020-07-31","deaths":1,"County Name":"Fulton County","State":"IN","stateFIPS":"18","case_count":134,"delta":4,"per_delta":0.0308,"r_t":0.9964,"infect_prob":1.7022,"r_t_three":1.0542,"r_t_seven":1.2545,"doubling":29},{"countyFIPS":"18049","pop":19974,"date":"2020-08-01","deaths":1,"County Name":"Fulton County","State":"IN","stateFIPS":"18","case_count":139,"delta":5,"per_delta":0.0373,"r_t":1.1996,"infect_prob":1.8524,"r_t_three":1.1712,"r_t_seven":1.2836,"doubling":27},{"countyFIPS":"18049","pop":19974,"date":"2020-08-02","deaths":2,"County Name":"Fulton County","State":"IN","stateFIPS":"18","case_count":144,"delta":5,"per_delta":0.036,"r_t":1.1642,"infect_prob":1.9525,"r_t_three":1.1201,"r_t_seven":1.4016,"doubling":26},{"countyFIPS":"18049","pop":19974,"date":"2020-08-03","deaths":2,"County Name":"Fulton County","State":"IN","stateFIPS":"18","case_count":146,"delta":2,"per_delta":0.0139,"r_t":0.4604,"infect_prob":1.9025,"r_t_three":0.9414,"r_t_seven":0.9873,"doubling":24},{"countyFIPS":"18049","pop":19974,"date":"2020-08-04","deaths":2,"County Name":"Fulton County","State":"IN","stateFIPS":"18","case_count":147,"delta":1,"per_delta":0.0068,"r_t":0.2381,"infect_prob":1.9025,"r_t_three":0.6209,"r_t_seven":0.8893,"doubling":23},{"countyFIPS":"18049","pop":19974,"date":"2020-08-05","deaths":2,"County Name":"Fulton County","State":"IN","stateFIPS":"18","case_count":150,"delta":3,"per_delta":0.0204,"r_t":0.7708,"infect_prob":1.552,"r_t_three":0.4898,"r_t_seven":0.8782,"doubling":24},{"countyFIPS":"18049","pop":19974,"date":"2020-08-06","deaths":2,"County Name":"Fulton County","State":"IN","stateFIPS":"18","case_count":159,"delta":9,"per_delta":0.06,"r_t":2.4407,"infect_prob":1.8524,"r_t_three":1.1499,"r_t_seven":1.0386,"doubling":23},{"countyFIPS":"18049","pop":19974,"date":"2020-08-07","deaths":2,"County Name":"Fulton County","State":"IN","stateFIPS":"18","case_count":161,"delta":2,"per_delta":0.0126,"r_t":0.5405,"infect_prob":1.8023,"r_t_three":1.2507,"r_t_seven":0.9735,"doubling":24},{"countyFIPS":"18049","pop":19974,"date":"2020-08-08","deaths":2,"County Name":"Fulton County","State":"IN","stateFIPS":"18","case_count":164,"delta":3,"per_delta":0.0186,"r_t":0.8041,"infect_prob":1.7022,"r_t_three":1.2618,"r_t_seven":0.917,"doubling":24},{"countyFIPS":"18049","pop":19974,"date":"2020-08-09","deaths":2,"County Name":"Fulton County","State":"IN","stateFIPS":"18","case_count":168,"delta":4,"per_delta":0.0244,"r_t":1.0616,"infect_prob":1.7022,"r_t_three":0.8021,"r_t_seven":0.9023,"doubling":24},{"countyFIPS":"18049","pop":19974,"date":"2020-08-10","deaths":2,"County Name":"Fulton County","State":"IN","stateFIPS":"18","case_count":169,"delta":1,"per_delta":0.006,"r_t":0.2677,"infect_prob":1.502,"r_t_three":0.7111,"r_t_seven":0.8748,"doubling":24},{"countyFIPS":"18049","pop":19974,"date":"2020-08-11","deaths":2,"County Name":"Fulton County","State":"IN","stateFIPS":"18","case_count":172,"delta":3,"per_delta":0.0178,"r_t":0.8409,"infect_prob":1.4018,"r_t_three":0.7234,"r_t_seven":0.9609,"doubling":25},{"countyFIPS":"18049","pop":19974,"date":"2020-08-12","deaths":2,"County Name":"Fulton County","State":"IN","stateFIPS":"18","case_count":173,"delta":1,"per_delta":0.0058,"r_t":0.3027,"infect_prob":1.3518,"r_t_three":0.4704,"r_t_seven":0.894,"doubling":25},{"countyFIPS":"18049","pop":19974,"date":"2020-08-13","deaths":2,"County Name":"Fulton County","State":"IN","stateFIPS":"18","case_count":174,"delta":1,"per_delta":0.0058,"r_t":0.3406,"infect_prob":1.3518,"r_t_three":0.4947,"r_t_seven":0.594,"doubling":26},{"countyFIPS":"18049","pop":19974,"date":"2020-08-14","deaths":2,"County Name":"Fulton County","State":"IN","stateFIPS":"18","case_count":175,"delta":1,"per_delta":0.0057,"r_t":0.3967,"infect_prob":1.2516,"r_t_three":0.3466,"r_t_seven":0.5735,"doubling":27},{"countyFIPS":"18049","pop":19974,"date":"2020-08-15","deaths":2,"County Name":"Fulton County","State":"IN","stateFIPS":"18","case_count":177,"delta":2,"per_delta":0.0114,"r_t":0.9349,"infect_prob":0.9012,"r_t_three":0.5574,"r_t_seven":0.5922,"doubling":28},{"countyFIPS":"18049","pop":19974,"date":"2020-08-16","deaths":2,"County Name":"Fulton County","State":"IN","stateFIPS":"18","case_count":178,"delta":1,"per_delta":0.0056,"r_t":0.5426,"infect_prob":0.8511,"r_t_three":0.6247,"r_t_seven":0.518,"doubling":29},{"countyFIPS":"18049","pop":19974,"date":"2020-08-17","deaths":2,"County Name":"Fulton County","State":"IN","stateFIPS":"18","case_count":180,"delta":2,"per_delta":0.0112,"r_t":1.2202,"infect_prob":0.801,"r_t_three":0.8992,"r_t_seven":0.6541,"doubling":29},{"countyFIPS":"18049","pop":19974,"date":"2020-08-18","deaths":2,"County Name":"Fulton County","State":"IN","stateFIPS":"18","case_count":184,"delta":4,"per_delta":0.0222,"r_t":2.5026,"infect_prob":0.801,"r_t_three":1.4218,"r_t_seven":0.8915,"doubling":29},{"countyFIPS":"18049","pop":19974,"date":"2020-08-19","deaths":2,"County Name":"Fulton County","State":"IN","stateFIPS":"18","case_count":184,"delta":0,"per_delta":0,"r_t":0,"infect_prob":0.751,"r_t_three":1.2409,"r_t_seven":0.8482,"doubling":30},{"countyFIPS":"18049","pop":19974,"date":"2020-08-20","deaths":2,"County Name":"Fulton County","State":"IN","stateFIPS":"18","case_count":186,"delta":2,"per_delta":0.0109,"r_t":1.1594,"infect_prob":0.7009,"r_t_three":1.2207,"r_t_seven":0.9652,"doubling":31},{"countyFIPS":"18049","pop":19974,"date":"2020-08-21","deaths":2,"County Name":"Fulton County","State":"IN","stateFIPS":"18","case_count":188,"delta":2,"per_delta":0.0108,"r_t":1.1269,"infect_prob":0.751,"r_t_three":0.7621,"r_t_seven":1.0695,"doubling":32},{"countyFIPS":"18049","pop":19974,"date":"2020-08-22","deaths":2,"County Name":"Fulton County","State":"IN","stateFIPS":"18","case_count":191,"delta":3,"per_delta":0.016,"r_t":1.6337,"infect_prob":0.8511,"r_t_three":1.3067,"r_t_seven":1.1693,"doubling":33},{"countyFIPS":"18049","pop":19974,"date":"2020-08-23","deaths":2,"County Name":"Fulton County","State":"IN","stateFIPS":"18","case_count":192,"delta":1,"per_delta":0.0052,"r_t":0.5268,"infect_prob":0.8511,"r_t_three":1.0958,"r_t_seven":1.1671,"doubling":34},{"countyFIPS":"18049","pop":19974,"date":"2020-08-24","deaths":2,"County Name":"Fulton County","State":"IN","stateFIPS":"18","case_count":198,"delta":6,"per_delta":0.0312,"r_t":2.9799,"infect_prob":1.0514,"r_t_three":1.7134,"r_t_seven":1.4185,"doubling":35},{"countyFIPS":"18049","pop":19974,"date":"2020-08-25","deaths":2,"County Name":"Fulton County","State":"IN","stateFIPS":"18","case_count":198,"delta":0,"per_delta":0,"r_t":0,"infect_prob":1.0013,"r_t_three":1.1689,"r_t_seven":1.061,"doubling":36},{"countyFIPS":"18049","pop":19974,"date":"2020-08-26","deaths":2,"County Name":"Fulton County","State":"IN","stateFIPS":"18","case_count":200,"delta":2,"per_delta":0.0101,"r_t":0.8714,"infect_prob":1.0013,"r_t_three":1.2838,"r_t_seven":1.1854,"doubling":36},{"countyFIPS":"18049","pop":19974,"date":"2020-08-27","deaths":2,"County Name":"Fulton County","State":"IN","stateFIPS":"18","case_count":203,"delta":3,"per_delta":0.015,"r_t":1.2818,"infect_prob":0.9512,"r_t_three":0.7177,"r_t_seven":1.2029,"doubling":36},{"countyFIPS":"18049","pop":19974,"date":"2020-08-28","deaths":2,"County Name":"Fulton County","State":"IN","stateFIPS":"18","case_count":203,"delta":0,"per_delta":0,"r_t":0,"infect_prob":0.9512,"r_t_three":0.7177,"r_t_seven":1.0419,"doubling":37},{"countyFIPS":"18049","pop":19974,"date":"2020-08-29","deaths":2,"County Name":"Fulton County","State":"IN","stateFIPS":"18","case_count":203,"delta":0,"per_delta":0,"r_t":0,"infect_prob":0.8511,"r_t_three":0.4273,"r_t_seven":0.8086,"doubling":38},{"countyFIPS":"18049","pop":19974,"date":"2020-08-30","deaths":2,"County Name":"Fulton County","State":"IN","stateFIPS":"18","case_count":207,"delta":4,"per_delta":0.0197,"r_t":2.0983,"infect_prob":0.9512,"r_t_three":0.6994,"r_t_seven":1.0331,"doubling":38},{"countyFIPS":"18049","pop":19974,"date":"2020-08-31","deaths":2,"County Name":"Fulton County","State":"IN","stateFIPS":"18","case_count":207,"delta":0,"per_delta":0,"r_t":0,"infect_prob":0.801,"r_t_three":0.6994,"r_t_seven":0.6074,"doubling":39},{"countyFIPS":"18049","pop":19974,"date":"2020-09-01","deaths":2,"County Name":"Fulton County","State":"IN","stateFIPS":"18","case_count":209,"delta":2,"per_delta":0.0097,"r_t":1.2415,"infect_prob":0.8511,"r_t_three":1.1133,"r_t_seven":0.7847,"doubling":40},{"countyFIPS":"18049","pop":19974,"date":"2020-09-02","deaths":2,"County Name":"Fulton County","State":"IN","stateFIPS":"18","case_count":209,"delta":0,"per_delta":0,"r_t":0,"infect_prob":0.5507,"r_t_three":0.4138,"r_t_seven":0.6602,"doubling":41},{"countyFIPS":"18049","pop":19974,"date":"2020-09-03","deaths":2,"County Name":"Fulton County","State":"IN","stateFIPS":"18","case_count":210,"delta":1,"per_delta":0.0048,"r_t":0.7285,"infect_prob":0.6008,"r_t_three":0.6567,"r_t_seven":0.5812,"doubling":42},{"countyFIPS":"18049","pop":19974,"date":"2020-09-04","deaths":2,"County Name":"Fulton County","State":"IN","stateFIPS":"18","case_count":210,"delta":0,"per_delta":0,"r_t":0,"infect_prob":0.5007,"r_t_three":0.2428,"r_t_seven":0.5812,"doubling":43},{"countyFIPS":"18049","pop":19974,"date":"2020-09-05","deaths":2,"County Name":"Fulton County","State":"IN","stateFIPS":"18","case_count":210,"delta":0,"per_delta":0,"r_t":0,"infect_prob":0.3505,"r_t_three":0.2428,"r_t_seven":0.5812,"doubling":44},{"countyFIPS":"18049","pop":19974,"date":"2020-09-06","deaths":2,"County Name":"Fulton County","State":"IN","stateFIPS":"18","case_count":211,"delta":1,"per_delta":0.0048,"r_t":1.1829,"infect_prob":0.4005,"r_t_three":0.3943,"r_t_seven":0.4504,"doubling":44},{"countyFIPS":"18049","pop":19974,"date":"2020-09-07","deaths":2,"County Name":"Fulton County","State":"IN","stateFIPS":"18","case_count":212,"delta":1,"per_delta":0.0047,"r_t":1.4062,"infect_prob":0.4506,"r_t_three":0.863,"r_t_seven":0.6513,"doubling":45},{"countyFIPS":"18049","pop":19974,"date":"2020-09-08","deaths":2,"County Name":"Fulton County","State":"IN","stateFIPS":"18","case_count":212,"delta":0,"per_delta":0,"r_t":0,"infect_prob":0.2503,"r_t_three":0.863,"r_t_seven":0.4739,"doubling":46},{"countyFIPS":"18049","pop":19974,"date":"2020-09-09","deaths":2,"County Name":"Fulton County","State":"IN","stateFIPS":"18","case_count":217,"delta":5,"per_delta":0.0236,"r_t":7.3909,"infect_prob":0.5007,"r_t_three":2.9324,"r_t_seven":1.5298,"doubling":46},{"countyFIPS":"18049","pop":19974,"date":"2020-09-10","deaths":2,"County Name":"Fulton County","State":"IN","stateFIPS":"18","case_count":218,"delta":1,"per_delta":0.0046,"r_t":1.0962,"infect_prob":0.4506,"r_t_three":2.829,"r_t_seven":1.5823,"doubling":47},{"countyFIPS":"18049","pop":19974,"date":"2020-09-11","deaths":2,"County Name":"Fulton County","State":"IN","stateFIPS":"18","case_count":219,"delta":1,"per_delta":0.0046,"r_t":0.8599,"infect_prob":0.5007,"r_t_three":3.1157,"r_t_seven":1.7052,"doubling":47},{"countyFIPS":"18049","pop":19974,"date":"2020-09-12","deaths":2,"County Name":"Fulton County","State":"IN","stateFIPS":"18","case_count":221,"delta":2,"per_delta":0.0091,"r_t":1.4534,"infect_prob":0.5507,"r_t_three":1.1365,"r_t_seven":1.9128,"doubling":48},{"countyFIPS":"18049","pop":19974,"date":"2020-09-13","deaths":2,"County Name":"Fulton County","State":"IN","stateFIPS":"18","case_count":225,"delta":4,"per_delta":0.0181,"r_t":2.5083,"infect_prob":0.751,"r_t_three":1.6072,"r_t_seven":2.1021,"doubling":49},{"countyFIPS":"18049","pop":19974,"date":"2020-09-14","deaths":2,"County Name":"Fulton County","State":"IN","stateFIPS":"18","case_count":226,"delta":1,"per_delta":0.0044,"r_t":0.5524,"infect_prob":0.801,"r_t_three":1.5047,"r_t_seven":1.9802,"doubling":50},{"countyFIPS":"18049","pop":19974,"date":"2020-09-15","deaths":2,"County Name":"Fulton County","State":"IN","stateFIPS":"18","case_count":228,"delta":2,"per_delta":0.0088,"r_t":1.0294,"infect_prob":0.8511,"r_t_three":1.3634,"r_t_seven":2.1272,"doubling":51},{"countyFIPS":"18049","pop":19974,"date":"2020-09-16","deaths":2,"County Name":"Fulton County","State":"IN","stateFIPS":"18","case_count":229,"delta":1,"per_delta":0.0044,"r_t":0.5018,"infect_prob":0.8511,"r_t_three":0.6946,"r_t_seven":1.1431,"doubling":52},{"countyFIPS":"18049","pop":19974,"date":"2020-09-17","deaths":2,"County Name":"Fulton County","State":"IN","stateFIPS":"18","case_count":231,"delta":2,"per_delta":0.0087,"r_t":1.0184,"infect_prob":0.9512,"r_t_three":0.8499,"r_t_seven":1.132,"doubling":53},{"countyFIPS":"18049","pop":19974,"date":"2020-09-18","deaths":2,"County Name":"Fulton County","State":"IN","stateFIPS":"18","case_count":231,"delta":0,"per_delta":0,"r_t":0,"infect_prob":0.7009,"r_t_three":0.5068,"r_t_seven":1.0091,"doubling":54},{"countyFIPS":"18049","pop":19974,"date":"2020-09-19","deaths":2,"County Name":"Fulton County","State":"IN","stateFIPS":"18","case_count":232,"delta":1,"per_delta":0.0043,"r_t":0.5949,"infect_prob":0.7009,"r_t_three":0.5378,"r_t_seven":0.8865,"doubling":55},{"countyFIPS":"18049","pop":19974,"date":"2020-09-20","deaths":2,"County Name":"Fulton County","State":"IN","stateFIPS":"18","case_count":236,"delta":4,"per_delta":0.0172,"r_t":2.5815,"infect_prob":0.8511,"r_t_three":1.0588,"r_t_seven":0.8969,"doubling":56},{"countyFIPS":"18049","pop":19974,"date":"2020-09-21","deaths":2,"County Name":"Fulton County","State":"IN","stateFIPS":"18","case_count":236,"delta":0,"per_delta":0,"r_t":0,"infect_prob":0.751,"r_t_three":1.0588,"r_t_seven":0.818,"doubling":57},{"countyFIPS":"18049","pop":19974,"date":"2020-09-22","deaths":2,"County Name":"Fulton County","State":"IN","stateFIPS":"18","case_count":236,"delta":0,"per_delta":0,"r_t":0,"infect_prob":0.5507,"r_t_three":0.8605,"r_t_seven":0.6709,"doubling":58},{"countyFIPS":"18049","pop":19974,"date":"2020-09-23","deaths":2,"County Name":"Fulton County","State":"IN","stateFIPS":"18","case_count":237,"delta":1,"per_delta":0.0042,"r_t":0.7502,"infect_prob":0.5507,"r_t_three":0.2501,"r_t_seven":0.7064,"doubling":59},{"countyFIPS":"18049","pop":19974,"date":"2020-09-24","deaths":2,"County Name":"Fulton County","State":"IN","stateFIPS":"18","case_count":237,"delta":0,"per_delta":0,"r_t":0,"infect_prob":0.4506,"r_t_three":0.2501,"r_t_seven":0.5609,"doubling":60},{"countyFIPS":"18049","pop":19974,"date":"2020-09-25","deaths":2,"County Name":"Fulton County","State":"IN","stateFIPS":"18","case_count":240,"delta":3,"per_delta":0.0127,"r_t":2.8126,"infect_prob":0.5507,"r_t_three":1.1876,"r_t_seven":0.9627,"doubling":60},{"countyFIPS":"18049","pop":19974,"date":"2020-09-26","deaths":2,"County Name":"Fulton County","State":"IN","stateFIPS":"18","case_count":243,"delta":3,"per_delta":0.0125,"r_t":2.7477,"infect_prob":0.6008,"r_t_three":1.8534,"r_t_seven":1.2703,"doubling":61},{"countyFIPS":"18049","pop":19974,"date":"2020-09-27","deaths":2,"County Name":"Fulton County","State":"IN","stateFIPS":"18","case_count":243,"delta":0,"per_delta":0,"r_t":0,"infect_prob":0.6008,"r_t_three":1.8534,"r_t_seven":0.9015,"doubling":62},{"countyFIPS":"18049","pop":19974,"date":"2020-09-28","deaths":2,"County Name":"Fulton County","State":"IN","stateFIPS":"18","case_count":246,"delta":3,"per_delta":0.0123,"r_t":2.2457,"infect_prob":0.7009,"r_t_three":1.6645,"r_t_seven":1.2223,"doubling":62},{"countyFIPS":"18049","pop":19974,"date":"2020-09-29","deaths":2,"County Name":"Fulton County","State":"IN","stateFIPS":"18","case_count":248,"delta":2,"per_delta":0.0081,"r_t":1.3204,"infect_prob":0.6008,"r_t_three":1.1887,"r_t_seven":1.411,"doubling":63},{"countyFIPS":"18049","pop":19974,"date":"2020-09-30","deaths":2,"County Name":"Fulton County","State":"IN","stateFIPS":"18","case_count":249,"delta":1,"per_delta":0.004,"r_t":0.6027,"infect_prob":0.6508,"r_t_three":1.3896,"r_t_seven":1.3899,"doubling":64},{"countyFIPS":"18049","pop":19974,"date":"2020-10-01","deaths":2,"County Name":"Fulton County","State":"IN","stateFIPS":"18","case_count":250,"delta":1,"per_delta":0.004,"r_t":0.584,"infect_prob":0.7009,"r_t_three":0.8357,"r_t_seven":1.4733,"doubling":65},{"countyFIPS":"18049","pop":19974,"date":"2020-10-02","deaths":2,"County Name":"Fulton County","State":"IN","stateFIPS":"18","case_count":261,"delta":11,"per_delta":0.044,"r_t":5.7558,"infect_prob":1.2016,"r_t_three":2.3142,"r_t_seven":1.8938,"doubling":64},{"countyFIPS":"18049","pop":19974,"date":"2020-10-03","deaths":2,"County Name":"Fulton County","State":"IN","stateFIPS":"18","case_count":263,"delta":2,"per_delta":0.0077,"r_t":0.8321,"infect_prob":1.3017,"r_t_three":2.3906,"r_t_seven":1.6201,"doubling":65},{"countyFIPS":"18049","pop":19974,"date":"2020-10-04","deaths":2,"County Name":"Fulton County","State":"IN","stateFIPS":"18","case_count":265,"delta":2,"per_delta":0.0076,"r_t":0.6993,"infect_prob":1.2516,"r_t_three":2.4291,"r_t_seven":1.72,"doubling":66},{"countyFIPS":"18049","pop":19974,"date":"2020-10-05","deaths":2,"County Name":"Fulton County","State":"IN","stateFIPS":"18","case_count":265,"delta":0,"per_delta":0,"r_t":0,"infect_prob":1.1014,"r_t_three":0.5105,"r_t_seven":1.3992,"doubling":67},{"countyFIPS":"18049","pop":19974,"date":"2020-10-06","deaths":2,"County Name":"Fulton County","State":"IN","stateFIPS":"18","case_count":266,"delta":1,"per_delta":0.0038,"r_t":0.327,"infect_prob":1.1515,"r_t_three":0.3421,"r_t_seven":1.2573,"doubling":68},{"countyFIPS":"18049","pop":19974,"date":"2020-10-07","deaths":2,"County Name":"Fulton County","State":"IN","stateFIPS":"18","case_count":269,"delta":3,"per_delta":0.0113,"r_t":1.0666,"infect_prob":1.1515,"r_t_three":0.4645,"r_t_seven":1.3235,"doubling":68},{"countyFIPS":"18049","pop":19974,"date":"2020-10-08","deaths":2,"County Name":"Fulton County","State":"IN","stateFIPS":"18","case_count":272,"delta":3,"per_delta":0.0112,"r_t":1.1773,"infect_prob":1.2016,"r_t_three":0.857,"r_t_seven":1.4083,"doubling":69},{"countyFIPS":"18049","pop":19974,"date":"2020-10-09","deaths":2,"County Name":"Fulton County","State":"IN","stateFIPS":"18","case_count":278,"delta":6,"per_delta":0.0221,"r_t":2.455,"infect_prob":1.4519,"r_t_three":1.5663,"r_t_seven":0.9368,"doubling":70},{"countyFIPS":"18049","pop":19974,"date":"2020-10-10","deaths":2,"County Name":"Fulton County","State":"IN","stateFIPS":"18","case_count":284,"delta":6,"per_delta":0.0216,"r_t":2.2667,"infect_prob":1.7022,"r_t_three":1.9663,"r_t_seven":1.1417,"doubling":70},{"countyFIPS":"18049","pop":19974,"date":"2020-10-11","deaths":2,"County Name":"Fulton County","State":"IN","stateFIPS":"18","case_count":286,"delta":2,"per_delta":0.007,"r_t":0.6608,"infect_prob":1.2516,"r_t_three":1.7942,"r_t_seven":1.1362,"doubling":71},{"countyFIPS":"18049","pop":19974,"date":"2020-10-12","deaths":2,"County Name":"Fulton County","State":"IN","stateFIPS":"18","case_count":293,"delta":7,"per_delta":0.0245,"r_t":2.0287,"infect_prob":1.502,"r_t_three":1.6521,"r_t_seven":1.426,"doubling":70}]
