[{"countyFIPS":"37025","pop":216453,"date":"2020-03-01","deaths":0,"County Name":"Cabarrus County","State":"NC","stateFIPS":"37","case_count":0,"delta":0,"infect_prob":0},{"countyFIPS":"37025","pop":216453,"date":"2020-03-02","deaths":0,"County Name":"Cabarrus County","State":"NC","stateFIPS":"37","case_count":0,"delta":0,"infect_prob":0},{"countyFIPS":"37025","pop":216453,"date":"2020-03-03","deaths":0,"County Name":"Cabarrus County","State":"NC","stateFIPS":"37","case_count":0,"delta":0,"infect_prob":0},{"countyFIPS":"37025","pop":216453,"date":"2020-03-04","deaths":0,"County Name":"Cabarrus County","State":"NC","stateFIPS":"37","case_count":0,"delta":0,"infect_prob":0},{"countyFIPS":"37025","pop":216453,"date":"2020-03-05","deaths":0,"County Name":"Cabarrus County","State":"NC","stateFIPS":"37","case_count":0,"delta":0,"infect_prob":0},{"countyFIPS":"37025","pop":216453,"date":"2020-03-06","deaths":0,"County Name":"Cabarrus County","State":"NC","stateFIPS":"37","case_count":0,"delta":0,"infect_prob":0},{"countyFIPS":"37025","pop":216453,"date":"2020-03-07","deaths":0,"County Name":"Cabarrus County","State":"NC","stateFIPS":"37","case_count":0,"delta":0,"infect_prob":0},{"countyFIPS":"37025","pop":216453,"date":"2020-03-08","deaths":0,"County Name":"Cabarrus County","State":"NC","stateFIPS":"37","case_count":0,"delta":0,"infect_prob":0},{"countyFIPS":"37025","pop":216453,"date":"2020-03-09","deaths":0,"County Name":"Cabarrus County","State":"NC","stateFIPS":"37","case_count":0,"delta":0,"infect_prob":0},{"countyFIPS":"37025","pop":216453,"date":"2020-03-10","deaths":0,"County Name":"Cabarrus County","State":"NC","stateFIPS":"37","case_count":0,"delta":0,"infect_prob":0},{"countyFIPS":"37025","pop":216453,"date":"2020-03-11","deaths":0,"County Name":"Cabarrus County","State":"NC","stateFIPS":"37","case_count":0,"delta":0,"infect_prob":0},{"countyFIPS":"37025","pop":216453,"date":"2020-03-12","deaths":0,"County Name":"Cabarrus County","State":"NC","stateFIPS":"37","case_count":0,"delta":0,"infect_prob":0},{"countyFIPS":"37025","pop":216453,"date":"2020-03-13","deaths":0,"County Name":"Cabarrus County","State":"NC","stateFIPS":"37","case_count":1,"delta":1,"r_t":41.9273,"infect_prob":0.0046,"doubling":1},{"countyFIPS":"37025","pop":216453,"date":"2020-03-14","deaths":0,"County Name":"Cabarrus County","State":"NC","stateFIPS":"37","case_count":1,"delta":0,"per_delta":0,"r_t":0,"infect_prob":0.0046,"doubling":2},{"countyFIPS":"37025","pop":216453,"date":"2020-03-15","deaths":0,"County Name":"Cabarrus County","State":"NC","stateFIPS":"37","case_count":1,"delta":0,"per_delta":0,"r_t":0,"infect_prob":0.0046,"r_t_three":13.9758,"doubling":3},{"countyFIPS":"37025","pop":216453,"date":"2020-03-16","deaths":0,"County Name":"Cabarrus County","State":"NC","stateFIPS":"37","case_count":1,"delta":0,"per_delta":0,"r_t":0,"infect_prob":0.0046,"r_t_three":0,"doubling":4},{"countyFIPS":"37025","pop":216453,"date":"2020-03-17","deaths":0,"County Name":"Cabarrus County","State":"NC","stateFIPS":"37","case_count":1,"delta":0,"per_delta":0,"r_t":0,"infect_prob":0.0046,"r_t_three":0,"doubling":5},{"countyFIPS":"37025","pop":216453,"date":"2020-03-18","deaths":0,"County Name":"Cabarrus County","State":"NC","stateFIPS":"37","case_count":1,"delta":0,"per_delta":0,"r_t":0,"infect_prob":0.0046,"r_t_three":0,"doubling":6},{"countyFIPS":"37025","pop":216453,"date":"2020-03-19","deaths":0,"County Name":"Cabarrus County","State":"NC","stateFIPS":"37","case_count":2,"delta":1,"per_delta":1,"r_t":7.2728,"infect_prob":0.0092,"r_t_three":2.4243,"r_t_seven":7.0286,"doubling":7},{"countyFIPS":"37025","pop":216453,"date":"2020-03-20","deaths":0,"County Name":"Cabarrus County","State":"NC","stateFIPS":"37","case_count":2,"delta":0,"per_delta":0,"r_t":0,"infect_prob":0.0092,"r_t_three":2.4243,"r_t_seven":1.039,"doubling":8},{"countyFIPS":"37025","pop":216453,"date":"2020-03-21","deaths":0,"County Name":"Cabarrus County","State":"NC","stateFIPS":"37","case_count":2,"delta":0,"per_delta":0,"r_t":0,"infect_prob":0.0092,"r_t_three":2.4243,"r_t_seven":1.039,"doubling":9},{"countyFIPS":"37025","pop":216453,"date":"2020-03-22","deaths":0,"County Name":"Cabarrus County","State":"NC","stateFIPS":"37","case_count":4,"delta":2,"per_delta":1,"r_t":8.4595,"infect_prob":0.0139,"r_t_three":2.8198,"r_t_seven":2.2475,"doubling":4},{"countyFIPS":"37025","pop":216453,"date":"2020-03-23","deaths":0,"County Name":"Cabarrus County","State":"NC","stateFIPS":"37","case_count":4,"delta":0,"per_delta":0,"r_t":0,"infect_prob":0.0139,"r_t_three":2.8198,"r_t_seven":2.2475,"doubling":5},{"countyFIPS":"37025","pop":216453,"date":"2020-03-24","deaths":0,"County Name":"Cabarrus County","State":"NC","stateFIPS":"37","case_count":8,"delta":4,"per_delta":1,"r_t":7.7986,"infect_prob":0.0323,"r_t_three":5.4194,"r_t_seven":3.3616,"doubling":3},{"countyFIPS":"37025","pop":216453,"date":"2020-03-25","deaths":1,"County Name":"Cabarrus County","State":"NC","stateFIPS":"37","case_count":12,"delta":4,"per_delta":0.5,"r_t":4.6386,"infect_prob":0.0508,"r_t_three":4.1457,"r_t_seven":4.0242,"doubling":2},{"countyFIPS":"37025","pop":216453,"date":"2020-03-26","deaths":1,"County Name":"Cabarrus County","State":"NC","stateFIPS":"37","case_count":16,"delta":4,"per_delta":0.3333,"r_t":2.9349,"infect_prob":0.0693,"r_t_three":5.124,"r_t_seven":3.4045,"doubling":3},{"countyFIPS":"37025","pop":216453,"date":"2020-03-27","deaths":1,"County Name":"Cabarrus County","State":"NC","stateFIPS":"37","case_count":21,"delta":5,"per_delta":0.3125,"r_t":2.5406,"infect_prob":0.0924,"r_t_three":3.3713,"r_t_seven":3.7675,"doubling":3},{"countyFIPS":"37025","pop":216453,"date":"2020-03-28","deaths":1,"County Name":"Cabarrus County","State":"NC","stateFIPS":"37","case_count":23,"delta":2,"per_delta":0.0952,"r_t":0.7827,"infect_prob":0.097,"r_t_three":2.0861,"r_t_seven":3.8793,"doubling":4},{"countyFIPS":"37025","pop":216453,"date":"2020-03-29","deaths":1,"County Name":"Cabarrus County","State":"NC","stateFIPS":"37","case_count":29,"delta":6,"per_delta":0.2609,"r_t":1.9728,"infect_prob":0.1247,"r_t_three":1.7654,"r_t_seven":2.9526,"doubling":4},{"countyFIPS":"37025","pop":216453,"date":"2020-03-30","deaths":1,"County Name":"Cabarrus County","State":"NC","stateFIPS":"37","case_count":38,"delta":9,"per_delta":0.3103,"r_t":2.507,"infect_prob":0.1663,"r_t_three":1.7542,"r_t_seven":3.3107,"doubling":4},{"countyFIPS":"37025","pop":216453,"date":"2020-03-31","deaths":1,"County Name":"Cabarrus County","State":"NC","stateFIPS":"37","case_count":45,"delta":7,"per_delta":0.1842,"r_t":1.6432,"infect_prob":0.1894,"r_t_three":2.041,"r_t_seven":2.4314,"doubling":4},{"countyFIPS":"37025","pop":216453,"date":"2020-04-01","deaths":1,"County Name":"Cabarrus County","State":"NC","stateFIPS":"37","case_count":45,"delta":0,"per_delta":0,"r_t":0,"infect_prob":0.1894,"r_t_three":1.3834,"r_t_seven":1.7687,"doubling":5},{"countyFIPS":"37025","pop":216453,"date":"2020-04-02","deaths":1,"County Name":"Cabarrus County","State":"NC","stateFIPS":"37","case_count":50,"delta":5,"per_delta":0.1111,"r_t":1.002,"infect_prob":0.194,"r_t_three":0.8817,"r_t_seven":1.4926,"doubling":5},{"countyFIPS":"37025","pop":216453,"date":"2020-04-03","deaths":1,"County Name":"Cabarrus County","State":"NC","stateFIPS":"37","case_count":56,"delta":6,"per_delta":0.12,"r_t":1.1922,"infect_prob":0.2033,"r_t_three":0.7314,"r_t_seven":1.3,"doubling":6},{"countyFIPS":"37025","pop":216453,"date":"2020-04-04","deaths":1,"County Name":"Cabarrus County","State":"NC","stateFIPS":"37","case_count":65,"delta":9,"per_delta":0.1607,"r_t":1.7634,"infect_prob":0.2264,"r_t_three":1.3192,"r_t_seven":1.4401,"doubling":6},{"countyFIPS":"37025","pop":216453,"date":"2020-04-05","deaths":1,"County Name":"Cabarrus County","State":"NC","stateFIPS":"37","case_count":67,"delta":2,"per_delta":0.0308,"r_t":0.3836,"infect_prob":0.2125,"r_t_three":1.1131,"r_t_seven":1.2131,"doubling":7},{"countyFIPS":"37025","pop":216453,"date":"2020-04-06","deaths":1,"County Name":"Cabarrus County","State":"NC","stateFIPS":"37","case_count":76,"delta":9,"per_delta":0.1343,"r_t":1.6948,"infect_prob":0.2449,"r_t_three":1.2806,"r_t_seven":1.097,"doubling":8},{"countyFIPS":"37025","pop":216453,"date":"2020-04-07","deaths":1,"County Name":"Cabarrus County","State":"NC","stateFIPS":"37","case_count":81,"delta":5,"per_delta":0.0658,"r_t":0.9078,"infect_prob":0.2402,"r_t_three":0.9954,"r_t_seven":0.992,"doubling":8},{"countyFIPS":"37025","pop":216453,"date":"2020-04-08","deaths":1,"County Name":"Cabarrus County","State":"NC","stateFIPS":"37","case_count":86,"delta":5,"per_delta":0.0617,"r_t":0.8837,"infect_prob":0.2218,"r_t_three":1.1621,"r_t_seven":1.1182,"doubling":9},{"countyFIPS":"37025","pop":216453,"date":"2020-04-09","deaths":1,"County Name":"Cabarrus County","State":"NC","stateFIPS":"37","case_count":86,"delta":0,"per_delta":0,"r_t":0,"infect_prob":0.1894,"r_t_three":0.5972,"r_t_seven":0.9751,"doubling":10},{"countyFIPS":"37025","pop":216453,"date":"2020-04-10","deaths":1,"County Name":"Cabarrus County","State":"NC","stateFIPS":"37","case_count":94,"delta":8,"per_delta":0.093,"r_t":1.4982,"infect_prob":0.2264,"r_t_three":0.7939,"r_t_seven":1.0188,"doubling":9},{"countyFIPS":"37025","pop":216453,"date":"2020-04-11","deaths":1,"County Name":"Cabarrus County","State":"NC","stateFIPS":"37","case_count":107,"delta":13,"per_delta":0.1383,"r_t":2.4374,"infect_prob":0.2633,"r_t_three":1.3119,"r_t_seven":1.1151,"doubling":9},{"countyFIPS":"37025","pop":216453,"date":"2020-04-12","deaths":1,"County Name":"Cabarrus County","State":"NC","stateFIPS":"37","case_count":117,"delta":10,"per_delta":0.0935,"r_t":1.7329,"infect_prob":0.2818,"r_t_three":1.8895,"r_t_seven":1.3078,"doubling":9},{"countyFIPS":"37025","pop":216453,"date":"2020-04-13","deaths":1,"County Name":"Cabarrus County","State":"NC","stateFIPS":"37","case_count":165,"delta":48,"per_delta":0.4103,"r_t":6.4625,"infect_prob":0.462,"r_t_three":3.5443,"r_t_seven":1.9889,"doubling":6},{"countyFIPS":"37025","pop":216453,"date":"2020-04-14","deaths":3,"County Name":"Cabarrus County","State":"NC","stateFIPS":"37","case_count":190,"delta":25,"per_delta":0.1515,"r_t":2.2993,"infect_prob":0.5683,"r_t_three":3.4982,"r_t_seven":2.1877,"doubling":4},{"countyFIPS":"37025","pop":216453,"date":"2020-04-15","deaths":3,"County Name":"Cabarrus County","State":"NC","stateFIPS":"37","case_count":191,"delta":1,"per_delta":0.0053,"r_t":0.0697,"infect_prob":0.5313,"r_t_three":2.9438,"r_t_seven":2.0714,"doubling":5},{"countyFIPS":"37025","pop":216453,"date":"2020-04-16","deaths":3,"County Name":"Cabarrus County","State":"NC","stateFIPS":"37","case_count":198,"delta":7,"per_delta":0.0366,"r_t":0.4274,"infect_prob":0.5405,"r_t_three":0.9322,"r_t_seven":2.1325,"doubling":6},{"countyFIPS":"37025","pop":216453,"date":"2020-04-17","deaths":3,"County Name":"Cabarrus County","State":"NC","stateFIPS":"37","case_count":201,"delta":3,"per_delta":0.0152,"r_t":0.1802,"infect_prob":0.5313,"r_t_three":0.2258,"r_t_seven":1.9442,"doubling":7},{"countyFIPS":"37025","pop":216453,"date":"2020-04-18","deaths":3,"County Name":"Cabarrus County","State":"NC","stateFIPS":"37","case_count":204,"delta":3,"per_delta":0.0149,"r_t":0.1967,"infect_prob":0.5452,"r_t_three":0.2681,"r_t_seven":1.6241,"doubling":8},{"countyFIPS":"37025","pop":216453,"date":"2020-04-19","deaths":3,"County Name":"Cabarrus County","State":"NC","stateFIPS":"37","case_count":208,"delta":4,"per_delta":0.0196,"r_t":0.3121,"infect_prob":0.5221,"r_t_three":0.2296,"r_t_seven":1.4211,"doubling":9},{"countyFIPS":"37025","pop":216453,"date":"2020-04-20","deaths":3,"County Name":"Cabarrus County","State":"NC","stateFIPS":"37","case_count":212,"delta":4,"per_delta":0.0192,"r_t":0.3949,"infect_prob":0.4851,"r_t_three":0.3012,"r_t_seven":0.5543,"doubling":10},{"countyFIPS":"37025","pop":216453,"date":"2020-04-21","deaths":5,"County Name":"Cabarrus County","State":"NC","stateFIPS":"37","case_count":216,"delta":4,"per_delta":0.0189,"r_t":0.514,"infect_prob":0.4574,"r_t_three":0.407,"r_t_seven":0.2993,"doubling":10},{"countyFIPS":"37025","pop":216453,"date":"2020-04-22","deaths":6,"County Name":"Cabarrus County","State":"NC","stateFIPS":"37","case_count":228,"delta":12,"per_delta":0.0556,"r_t":1.9193,"infect_prob":0.2911,"r_t_three":0.9427,"r_t_seven":0.5635,"doubling":11},{"countyFIPS":"37025","pop":216453,"date":"2020-04-23","deaths":6,"County Name":"Cabarrus County","State":"NC","stateFIPS":"37","case_count":231,"delta":3,"per_delta":0.0132,"r_t":0.535,"infect_prob":0.1894,"r_t_three":0.9894,"r_t_seven":0.5789,"doubling":12},{"countyFIPS":"37025","pop":216453,"date":"2020-04-24","deaths":6,"County Name":"Cabarrus County","State":"NC","stateFIPS":"37","case_count":239,"delta":8,"per_delta":0.0346,"r_t":1.4619,"infect_prob":0.2218,"r_t_three":1.3054,"r_t_seven":0.762,"doubling":12},{"countyFIPS":"37025","pop":216453,"date":"2020-04-25","deaths":8,"County Name":"Cabarrus County","State":"NC","stateFIPS":"37","case_count":247,"delta":8,"per_delta":0.0335,"r_t":1.3988,"infect_prob":0.2264,"r_t_three":1.1319,"r_t_seven":0.9337,"doubling":13},{"countyFIPS":"37025","pop":216453,"date":"2020-04-26","deaths":8,"County Name":"Cabarrus County","State":"NC","stateFIPS":"37","case_count":250,"delta":3,"per_delta":0.0121,"r_t":0.4978,"infect_prob":0.2264,"r_t_three":1.1195,"r_t_seven":0.9602,"doubling":14},{"countyFIPS":"37025","pop":216453,"date":"2020-04-27","deaths":9,"County Name":"Cabarrus County","State":"NC","stateFIPS":"37","case_count":254,"delta":4,"per_delta":0.016,"r_t":0.6551,"infect_prob":0.231,"r_t_three":0.8506,"r_t_seven":0.9974,"doubling":15},{"countyFIPS":"37025","pop":216453,"date":"2020-04-28","deaths":9,"County Name":"Cabarrus County","State":"NC","stateFIPS":"37","case_count":258,"delta":4,"per_delta":0.0157,"r_t":0.6734,"infect_prob":0.231,"r_t_three":0.6088,"r_t_seven":1.0202,"doubling":16},{"countyFIPS":"37025","pop":216453,"date":"2020-04-29","deaths":10,"County Name":"Cabarrus County","State":"NC","stateFIPS":"37","case_count":267,"delta":9,"per_delta":0.0349,"r_t":1.5749,"infect_prob":0.2541,"r_t_three":0.9678,"r_t_seven":0.971,"doubling":17},{"countyFIPS":"37025","pop":216453,"date":"2020-04-30","deaths":11,"County Name":"Cabarrus County","State":"NC","stateFIPS":"37","case_count":296,"delta":29,"per_delta":0.1086,"r_t":4.6934,"infect_prob":0.3696,"r_t_three":2.3139,"r_t_seven":1.565,"doubling":18},{"countyFIPS":"37025","pop":216453,"date":"2020-05-01","deaths":11,"County Name":"Cabarrus County","State":"NC","stateFIPS":"37","case_count":308,"delta":12,"per_delta":0.0405,"r_t":1.5652,"infect_prob":0.3696,"r_t_three":2.6112,"r_t_seven":1.5798,"doubling":19},{"countyFIPS":"37025","pop":216453,"date":"2020-05-02","deaths":12,"County Name":"Cabarrus County","State":"NC","stateFIPS":"37","case_count":310,"delta":2,"per_delta":0.0065,"r_t":0.2175,"infect_prob":0.365,"r_t_three":2.1587,"r_t_seven":1.411,"doubling":20},{"countyFIPS":"37025","pop":216453,"date":"2020-05-03","deaths":12,"County Name":"Cabarrus County","State":"NC","stateFIPS":"37","case_count":313,"delta":3,"per_delta":0.0097,"r_t":0.2993,"infect_prob":0.3419,"r_t_three":0.694,"r_t_seven":1.3827,"doubling":21},{"countyFIPS":"37025","pop":216453,"date":"2020-05-04","deaths":13,"County Name":"Cabarrus County","State":"NC","stateFIPS":"37","case_count":314,"delta":1,"per_delta":0.0032,"r_t":0.1011,"infect_prob":0.3095,"r_t_three":0.2059,"r_t_seven":1.3035,"doubling":22},{"countyFIPS":"37025","pop":216453,"date":"2020-05-05","deaths":15,"County Name":"Cabarrus County","State":"NC","stateFIPS":"37","case_count":318,"delta":4,"per_delta":0.0127,"r_t":0.4487,"infect_prob":0.3142,"r_t_three":0.283,"r_t_seven":1.2714,"doubling":23},{"countyFIPS":"37025","pop":216453,"date":"2020-05-06","deaths":16,"County Name":"Cabarrus County","State":"NC","stateFIPS":"37","case_count":323,"delta":5,"per_delta":0.0157,"r_t":0.6619,"infect_prob":0.3188,"r_t_three":0.4039,"r_t_seven":1.141,"doubling":24},{"countyFIPS":"37025","pop":216453,"date":"2020-05-07","deaths":17,"County Name":"Cabarrus County","State":"NC","stateFIPS":"37","case_count":333,"delta":10,"per_delta":0.031,"r_t":1.5679,"infect_prob":0.3465,"r_t_three":0.8928,"r_t_seven":0.6945,"doubling":24},{"countyFIPS":"37025","pop":216453,"date":"2020-05-08","deaths":17,"County Name":"Cabarrus County","State":"NC","stateFIPS":"37","case_count":338,"delta":5,"per_delta":0.015,"r_t":0.8748,"infect_prob":0.328,"r_t_three":1.0349,"r_t_seven":0.5959,"doubling":25},{"countyFIPS":"37025","pop":216453,"date":"2020-05-09","deaths":17,"County Name":"Cabarrus County","State":"NC","stateFIPS":"37","case_count":341,"delta":3,"per_delta":0.0089,"r_t":0.5559,"infect_prob":0.2079,"r_t_three":0.9995,"r_t_seven":0.6442,"doubling":26},{"countyFIPS":"37025","pop":216453,"date":"2020-05-10","deaths":17,"County Name":"Cabarrus County","State":"NC","stateFIPS":"37","case_count":350,"delta":9,"per_delta":0.0264,"r_t":1.6828,"infect_prob":0.194,"r_t_three":1.0378,"r_t_seven":0.8419,"doubling":27},{"countyFIPS":"37025","pop":216453,"date":"2020-05-11","deaths":17,"County Name":"Cabarrus County","State":"NC","stateFIPS":"37","case_count":350,"delta":0,"per_delta":0,"r_t":0,"infect_prob":0.1848,"r_t_three":0.7462,"r_t_seven":0.8274,"doubling":28},{"countyFIPS":"37025","pop":216453,"date":"2020-05-12","deaths":18,"County Name":"Cabarrus County","State":"NC","stateFIPS":"37","case_count":356,"delta":6,"per_delta":0.0171,"r_t":1.1343,"infect_prob":0.1987,"r_t_three":0.939,"r_t_seven":0.9254,"doubling":29},{"countyFIPS":"37025","pop":216453,"date":"2020-05-13","deaths":18,"County Name":"Cabarrus County","State":"NC","stateFIPS":"37","case_count":361,"delta":5,"per_delta":0.014,"r_t":0.9717,"infect_prob":0.2171,"r_t_three":0.702,"r_t_seven":0.9696,"doubling":30},{"countyFIPS":"37025","pop":216453,"date":"2020-05-14","deaths":18,"County Name":"Cabarrus County","State":"NC","stateFIPS":"37","case_count":362,"delta":1,"per_delta":0.0028,"r_t":0.204,"infect_prob":0.2033,"r_t_three":0.77,"r_t_seven":0.7748,"doubling":31},{"countyFIPS":"37025","pop":216453,"date":"2020-05-15","deaths":19,"County Name":"Cabarrus County","State":"NC","stateFIPS":"37","case_count":370,"delta":8,"per_delta":0.0221,"r_t":1.7253,"infect_prob":0.2171,"r_t_three":0.967,"r_t_seven":0.8963,"doubling":32},{"countyFIPS":"37025","pop":216453,"date":"2020-05-16","deaths":19,"County Name":"Cabarrus County","State":"NC","stateFIPS":"37","case_count":372,"delta":2,"per_delta":0.0054,"r_t":0.4457,"infect_prob":0.1802,"r_t_three":0.7917,"r_t_seven":0.8805,"doubling":33},{"countyFIPS":"37025","pop":216453,"date":"2020-05-17","deaths":19,"County Name":"Cabarrus County","State":"NC","stateFIPS":"37","case_count":379,"delta":7,"per_delta":0.0188,"r_t":1.5899,"infect_prob":0.1894,"r_t_three":1.2536,"r_t_seven":0.8673,"doubling":34},{"countyFIPS":"37025","pop":216453,"date":"2020-05-18","deaths":19,"County Name":"Cabarrus County","State":"NC","stateFIPS":"37","case_count":379,"delta":0,"per_delta":0,"r_t":0,"infect_prob":0.1756,"r_t_three":0.6785,"r_t_seven":0.8673,"doubling":35},{"countyFIPS":"37025","pop":216453,"date":"2020-05-19","deaths":20,"County Name":"Cabarrus County","State":"NC","stateFIPS":"37","case_count":389,"delta":10,"per_delta":0.0264,"r_t":2.3095,"infect_prob":0.1802,"r_t_three":1.2998,"r_t_seven":1.0352,"doubling":34},{"countyFIPS":"37025","pop":216453,"date":"2020-05-20","deaths":21,"County Name":"Cabarrus County","State":"NC","stateFIPS":"37","case_count":395,"delta":6,"per_delta":0.0154,"r_t":1.3214,"infect_prob":0.2079,"r_t_three":1.2103,"r_t_seven":1.0851,"doubling":35},{"countyFIPS":"37025","pop":216453,"date":"2020-05-21","deaths":21,"County Name":"Cabarrus County","State":"NC","stateFIPS":"37","case_count":406,"delta":11,"per_delta":0.0278,"r_t":2.2102,"infect_prob":0.231,"r_t_three":1.947,"r_t_seven":1.3717,"doubling":34},{"countyFIPS":"37025","pop":216453,"date":"2020-05-22","deaths":21,"County Name":"Cabarrus County","State":"NC","stateFIPS":"37","case_count":420,"delta":14,"per_delta":0.0345,"r_t":2.411,"infect_prob":0.2726,"r_t_three":1.9809,"r_t_seven":1.4697,"doubling":33},{"countyFIPS":"37025","pop":216453,"date":"2020-05-23","deaths":21,"County Name":"Cabarrus County","State":"NC","stateFIPS":"37","case_count":428,"delta":8,"per_delta":0.019,"r_t":1.161,"infect_prob":0.3049,"r_t_three":1.9274,"r_t_seven":1.5719,"doubling":33},{"countyFIPS":"37025","pop":216453,"date":"2020-05-24","deaths":21,"County Name":"Cabarrus County","State":"NC","stateFIPS":"37","case_count":429,"delta":1,"per_delta":0.0023,"r_t":0.13,"infect_prob":0.2726,"r_t_three":1.234,"r_t_seven":1.3633,"doubling":34},{"countyFIPS":"37025","pop":216453,"date":"2020-05-25","deaths":21,"County Name":"Cabarrus County","State":"NC","stateFIPS":"37","case_count":446,"delta":17,"per_delta":0.0396,"r_t":2.078,"infect_prob":0.3419,"r_t_three":1.123,"r_t_seven":1.6602,"doubling":34},{"countyFIPS":"37025","pop":216453,"date":"2020-05-26","deaths":21,"County Name":"Cabarrus County","State":"NC","stateFIPS":"37","case_count":446,"delta":0,"per_delta":0,"r_t":0,"infect_prob":0.3095,"r_t_three":0.736,"r_t_seven":1.3302,"doubling":35},{"countyFIPS":"37025","pop":216453,"date":"2020-05-27","deaths":21,"County Name":"Cabarrus County","State":"NC","stateFIPS":"37","case_count":448,"delta":2,"per_delta":0.0045,"r_t":0.245,"infect_prob":0.3188,"r_t_three":0.7743,"r_t_seven":1.1765,"doubling":36},{"countyFIPS":"37025","pop":216453,"date":"2020-05-28","deaths":21,"County Name":"Cabarrus County","State":"NC","stateFIPS":"37","case_count":455,"delta":7,"per_delta":0.0156,"r_t":0.9359,"infect_prob":0.3049,"r_t_three":0.3936,"r_t_seven":0.9944,"doubling":37},{"countyFIPS":"37025","pop":216453,"date":"2020-05-29","deaths":21,"County Name":"Cabarrus County","State":"NC","stateFIPS":"37","case_count":460,"delta":5,"per_delta":0.011,"r_t":0.7406,"infect_prob":0.3003,"r_t_three":0.6405,"r_t_seven":0.7558,"doubling":37},{"countyFIPS":"37025","pop":216453,"date":"2020-05-30","deaths":21,"County Name":"Cabarrus County","State":"NC","stateFIPS":"37","case_count":478,"delta":18,"per_delta":0.0391,"r_t":2.8088,"infect_prob":0.3326,"r_t_three":1.4951,"r_t_seven":0.9912,"doubling":37},{"countyFIPS":"37025","pop":216453,"date":"2020-05-31","deaths":21,"County Name":"Cabarrus County","State":"NC","stateFIPS":"37","case_count":478,"delta":0,"per_delta":0,"r_t":0,"infect_prob":0.268,"r_t_three":1.1831,"r_t_seven":0.9726,"doubling":38},{"countyFIPS":"37025","pop":216453,"date":"2020-06-01","deaths":21,"County Name":"Cabarrus County","State":"NC","stateFIPS":"37","case_count":497,"delta":19,"per_delta":0.0397,"r_t":2.7341,"infect_prob":0.3188,"r_t_three":1.8476,"r_t_seven":1.0663,"doubling":37},{"countyFIPS":"37025","pop":216453,"date":"2020-06-02","deaths":21,"County Name":"Cabarrus County","State":"NC","stateFIPS":"37","case_count":498,"delta":1,"per_delta":0.002,"r_t":0.1311,"infect_prob":0.3188,"r_t_three":0.9551,"r_t_seven":1.0851,"doubling":38},{"countyFIPS":"37025","pop":216453,"date":"2020-06-03","deaths":22,"County Name":"Cabarrus County","State":"NC","stateFIPS":"37","case_count":500,"delta":2,"per_delta":0.004,"r_t":0.2543,"infect_prob":0.2495,"r_t_three":1.0398,"r_t_seven":1.0864,"doubling":39},{"countyFIPS":"37025","pop":216453,"date":"2020-06-04","deaths":23,"County Name":"Cabarrus County","State":"NC","stateFIPS":"37","case_count":521,"delta":21,"per_delta":0.042,"r_t":2.6284,"infect_prob":0.3465,"r_t_three":1.0046,"r_t_seven":1.3282,"doubling":37},{"countyFIPS":"37025","pop":216453,"date":"2020-06-05","deaths":23,"County Name":"Cabarrus County","State":"NC","stateFIPS":"37","case_count":536,"delta":15,"per_delta":0.0288,"r_t":1.7483,"infect_prob":0.4066,"r_t_three":1.5436,"r_t_seven":1.4721,"doubling":37},{"countyFIPS":"37025","pop":216453,"date":"2020-06-06","deaths":23,"County Name":"Cabarrus County","State":"NC","stateFIPS":"37","case_count":571,"delta":35,"per_delta":0.0653,"r_t":3.4973,"infect_prob":0.5359,"r_t_three":2.6246,"r_t_seven":1.5705,"doubling":38},{"countyFIPS":"37025","pop":216453,"date":"2020-06-07","deaths":23,"County Name":"Cabarrus County","State":"NC","stateFIPS":"37","case_count":588,"delta":17,"per_delta":0.0298,"r_t":1.371,"infect_prob":0.5914,"r_t_three":2.2055,"r_t_seven":1.7664,"doubling":39},{"countyFIPS":"37025","pop":216453,"date":"2020-06-08","deaths":23,"County Name":"Cabarrus County","State":"NC","stateFIPS":"37","case_count":599,"delta":11,"per_delta":0.0187,"r_t":0.7489,"infect_prob":0.559,"r_t_three":1.8724,"r_t_seven":1.4827,"doubling":39},{"countyFIPS":"37025","pop":216453,"date":"2020-06-09","deaths":23,"County Name":"Cabarrus County","State":"NC","stateFIPS":"37","case_count":612,"delta":13,"per_delta":0.0217,"r_t":0.8017,"infect_prob":0.6191,"r_t_three":0.9739,"r_t_seven":1.5785,"doubling":40},{"countyFIPS":"37025","pop":216453,"date":"2020-06-10","deaths":23,"County Name":"Cabarrus County","State":"NC","stateFIPS":"37","case_count":614,"delta":2,"per_delta":0.0033,"r_t":0.1208,"infect_prob":0.5405,"r_t_three":0.5571,"r_t_seven":1.5595,"doubling":41},{"countyFIPS":"37025","pop":216453,"date":"2020-06-11","deaths":24,"County Name":"Cabarrus County","State":"NC","stateFIPS":"37","case_count":641,"delta":27,"per_delta":0.044,"r_t":1.6842,"infect_prob":0.6607,"r_t_three":0.8689,"r_t_seven":1.4246,"doubling":37},{"countyFIPS":"37025","pop":216453,"date":"2020-06-12","deaths":24,"County Name":"Cabarrus County","State":"NC","stateFIPS":"37","case_count":670,"delta":29,"per_delta":0.0452,"r_t":1.8212,"infect_prob":0.7854,"r_t_three":1.2088,"r_t_seven":1.435,"doubling":36},{"countyFIPS":"37025","pop":216453,"date":"2020-06-13","deaths":24,"County Name":"Cabarrus County","State":"NC","stateFIPS":"37","case_count":686,"delta":16,"per_delta":0.0239,"r_t":0.9746,"infect_prob":0.7623,"r_t_three":1.4933,"r_t_seven":1.0746,"doubling":35},{"countyFIPS":"37025","pop":216453,"date":"2020-06-14","deaths":24,"County Name":"Cabarrus County","State":"NC","stateFIPS":"37","case_count":711,"delta":25,"per_delta":0.0364,"r_t":1.4449,"infect_prob":0.8085,"r_t_three":1.4136,"r_t_seven":1.0852,"doubling":34},{"countyFIPS":"37025","pop":216453,"date":"2020-06-15","deaths":24,"County Name":"Cabarrus County","State":"NC","stateFIPS":"37","case_count":716,"delta":5,"per_delta":0.007,"r_t":0.2756,"infect_prob":0.6699,"r_t_three":0.8983,"r_t_seven":1.0176,"doubling":34},{"countyFIPS":"37025","pop":216453,"date":"2020-06-16","deaths":25,"County Name":"Cabarrus County","State":"NC","stateFIPS":"37","case_count":729,"delta":13,"per_delta":0.0182,"r_t":0.7144,"infect_prob":0.6514,"r_t_three":0.8116,"r_t_seven":1.0051,"doubling":33},{"countyFIPS":"37025","pop":216453,"date":"2020-06-17","deaths":25,"County Name":"Cabarrus County","State":"NC","stateFIPS":"37","case_count":746,"delta":17,"per_delta":0.0233,"r_t":0.9608,"infect_prob":0.6791,"r_t_three":0.6502,"r_t_seven":1.1251,"doubling":32},{"countyFIPS":"37025","pop":216453,"date":"2020-06-18","deaths":25,"County Name":"Cabarrus County","State":"NC","stateFIPS":"37","case_count":773,"delta":27,"per_delta":0.0362,"r_t":1.5675,"infect_prob":0.7438,"r_t_three":1.0809,"r_t_seven":1.1084,"doubling":31},{"countyFIPS":"37025","pop":216453,"date":"2020-06-19","deaths":25,"County Name":"Cabarrus County","State":"NC","stateFIPS":"37","case_count":805,"delta":32,"per_delta":0.0414,"r_t":1.8248,"infect_prob":0.8778,"r_t_three":1.451,"r_t_seven":1.1089,"doubling":30},{"countyFIPS":"37025","pop":216453,"date":"2020-06-20","deaths":25,"County Name":"Cabarrus County","State":"NC","stateFIPS":"37","case_count":835,"delta":30,"per_delta":0.0373,"r_t":1.5896,"infect_prob":0.8963,"r_t_three":1.6606,"r_t_seven":1.1968,"doubling":30},{"countyFIPS":"37025","pop":216453,"date":"2020-06-21","deaths":25,"County Name":"Cabarrus County","State":"NC","stateFIPS":"37","case_count":869,"delta":34,"per_delta":0.0407,"r_t":1.6152,"infect_prob":0.9194,"r_t_three":1.6765,"r_t_seven":1.2211,"doubling":28},{"countyFIPS":"37025","pop":216453,"date":"2020-06-22","deaths":25,"County Name":"Cabarrus County","State":"NC","stateFIPS":"37","case_count":883,"delta":14,"per_delta":0.0161,"r_t":0.6015,"infect_prob":0.9101,"r_t_three":1.2688,"r_t_seven":1.2677,"doubling":29},{"countyFIPS":"37025","pop":216453,"date":"2020-06-23","deaths":26,"County Name":"Cabarrus County","State":"NC","stateFIPS":"37","case_count":888,"delta":5,"per_delta":0.0057,"r_t":0.2067,"infect_prob":0.8177,"r_t_three":0.8078,"r_t_seven":1.1951,"doubling":30},{"countyFIPS":"37025","pop":216453,"date":"2020-06-24","deaths":27,"County Name":"Cabarrus County","State":"NC","stateFIPS":"37","case_count":912,"delta":24,"per_delta":0.027,"r_t":1.0133,"infect_prob":0.9055,"r_t_three":0.6072,"r_t_seven":1.2026,"doubling":27},{"countyFIPS":"37025","pop":216453,"date":"2020-06-25","deaths":27,"County Name":"Cabarrus County","State":"NC","stateFIPS":"37","case_count":936,"delta":24,"per_delta":0.0263,"r_t":1.0585,"infect_prob":0.9517,"r_t_three":0.7595,"r_t_seven":1.1299,"doubling":27},{"countyFIPS":"37025","pop":216453,"date":"2020-06-26","deaths":27,"County Name":"Cabarrus County","State":"NC","stateFIPS":"37","case_count":978,"delta":42,"per_delta":0.0449,"r_t":1.8952,"infect_prob":1.0672,"r_t_three":1.3223,"r_t_seven":1.14,"doubling":26},{"countyFIPS":"37025","pop":216453,"date":"2020-06-27","deaths":27,"County Name":"Cabarrus County","State":"NC","stateFIPS":"37","case_count":1021,"delta":43,"per_delta":0.044,"r_t":1.8564,"infect_prob":1.1411,"r_t_three":1.6034,"r_t_seven":1.1781,"doubling":24},{"countyFIPS":"37025","pop":216453,"date":"2020-06-28","deaths":27,"County Name":"Cabarrus County","State":"NC","stateFIPS":"37","case_count":1064,"delta":43,"per_delta":0.0421,"r_t":1.6734,"infect_prob":1.1966,"r_t_three":1.8083,"r_t_seven":1.1864,"doubling":24},{"countyFIPS":"37025","pop":216453,"date":"2020-06-29","deaths":28,"County Name":"Cabarrus County","State":"NC","stateFIPS":"37","case_count":1105,"delta":41,"per_delta":0.0385,"r_t":1.4048,"infect_prob":1.2474,"r_t_three":1.6449,"r_t_seven":1.3012,"doubling":24},{"countyFIPS":"37025","pop":216453,"date":"2020-06-30","deaths":28,"County Name":"Cabarrus County","State":"NC","stateFIPS":"37","case_count":1107,"delta":2,"per_delta":0.0018,"r_t":0.0627,"infect_prob":1.0995,"r_t_three":1.047,"r_t_seven":1.2806,"doubling":25},{"countyFIPS":"37025","pop":216453,"date":"2020-07-01","deaths":33,"County Name":"Cabarrus County","State":"NC","stateFIPS":"37","case_count":1141,"delta":34,"per_delta":0.0307,"r_t":1.0426,"infect_prob":1.1873,"r_t_three":0.8367,"r_t_seven":1.2848,"doubling":26},{"countyFIPS":"37025","pop":216453,"date":"2020-07-02","deaths":33,"County Name":"Cabarrus County","State":"NC","stateFIPS":"37","case_count":1187,"delta":46,"per_delta":0.0403,"r_t":1.4094,"infect_prob":1.3767,"r_t_three":0.8382,"r_t_seven":1.3349,"doubling":25},{"countyFIPS":"37025","pop":216453,"date":"2020-07-03","deaths":33,"County Name":"Cabarrus County","State":"NC","stateFIPS":"37","case_count":1237,"delta":50,"per_delta":0.0421,"r_t":1.5121,"infect_prob":1.4969,"r_t_three":1.3213,"r_t_seven":1.2802,"doubling":23},{"countyFIPS":"37025","pop":216453,"date":"2020-07-04","deaths":33,"County Name":"Cabarrus County","State":"NC","stateFIPS":"37","case_count":1313,"delta":76,"per_delta":0.0614,"r_t":2.1641,"infect_prob":1.7371,"r_t_three":1.6952,"r_t_seven":1.3241,"doubling":23},{"countyFIPS":"37025","pop":216453,"date":"2020-07-05","deaths":33,"County Name":"Cabarrus County","State":"NC","stateFIPS":"37","case_count":1343,"delta":30,"per_delta":0.0228,"r_t":0.7776,"infect_prob":1.6817,"r_t_three":1.4846,"r_t_seven":1.1962,"doubling":23},{"countyFIPS":"37025","pop":216453,"date":"2020-07-06","deaths":33,"County Name":"Cabarrus County","State":"NC","stateFIPS":"37","case_count":1368,"delta":25,"per_delta":0.0186,"r_t":0.6068,"infect_prob":1.5985,"r_t_three":1.1828,"r_t_seven":1.0822,"doubling":24},{"countyFIPS":"37025","pop":216453,"date":"2020-07-07","deaths":33,"County Name":"Cabarrus County","State":"NC","stateFIPS":"37","case_count":1399,"delta":31,"per_delta":0.0227,"r_t":0.736,"infect_prob":1.5431,"r_t_three":0.7068,"r_t_seven":1.1784,"doubling":24},{"countyFIPS":"37025","pop":216453,"date":"2020-07-08","deaths":33,"County Name":"Cabarrus County","State":"NC","stateFIPS":"37","case_count":1424,"delta":25,"per_delta":0.0179,"r_t":0.6065,"infect_prob":1.4691,"r_t_three":0.6497,"r_t_seven":1.1161,"doubling":24},{"countyFIPS":"37025","pop":216453,"date":"2020-07-09","deaths":33,"County Name":"Cabarrus County","State":"NC","stateFIPS":"37","case_count":1454,"delta":30,"per_delta":0.0211,"r_t":0.7714,"infect_prob":1.5985,"r_t_three":0.7046,"r_t_seven":1.0249,"doubling":24},{"countyFIPS":"37025","pop":216453,"date":"2020-07-10","deaths":33,"County Name":"Cabarrus County","State":"NC","stateFIPS":"37","case_count":1521,"delta":67,"per_delta":0.0461,"r_t":1.8133,"infect_prob":1.751,"r_t_three":1.0637,"r_t_seven":1.068,"doubling":23},{"countyFIPS":"37025","pop":216453,"date":"2020-07-11","deaths":33,"County Name":"Cabarrus County","State":"NC","stateFIPS":"37","case_count":1580,"delta":59,"per_delta":0.0388,"r_t":1.5858,"infect_prob":1.811,"r_t_three":1.3902,"r_t_seven":0.9853,"doubling":23},{"countyFIPS":"37025","pop":216453,"date":"2020-07-12","deaths":33,"County Name":"Cabarrus County","State":"NC","stateFIPS":"37","case_count":1640,"delta":60,"per_delta":0.038,"r_t":1.5147,"infect_prob":1.8572,"r_t_three":1.6379,"r_t_seven":1.0906,"doubling":23},{"countyFIPS":"37025","pop":216453,"date":"2020-07-13","deaths":33,"County Name":"Cabarrus County","State":"NC","stateFIPS":"37","case_count":1677,"delta":37,"per_delta":0.0226,"r_t":0.8606,"infect_prob":1.677,"r_t_three":1.3204,"r_t_seven":1.1269,"doubling":23},{"countyFIPS":"37025","pop":216453,"date":"2020-07-14","deaths":33,"County Name":"Cabarrus County","State":"NC","stateFIPS":"37","case_count":1721,"delta":44,"per_delta":0.0262,"r_t":0.9617,"infect_prob":1.7417,"r_t_three":1.1124,"r_t_seven":1.1592,"doubling":24},{"countyFIPS":"37025","pop":216453,"date":"2020-07-15","deaths":33,"County Name":"Cabarrus County","State":"NC","stateFIPS":"37","case_count":1754,"delta":33,"per_delta":0.0192,"r_t":0.7005,"infect_prob":1.7787,"r_t_three":0.841,"r_t_seven":1.1726,"doubling":24},{"countyFIPS":"37025","pop":216453,"date":"2020-07-16","deaths":33,"County Name":"Cabarrus County","State":"NC","stateFIPS":"37","case_count":1795,"delta":41,"per_delta":0.0234,"r_t":0.8762,"infect_prob":1.8249,"r_t_three":0.8461,"r_t_seven":1.1876,"doubling":23},{"countyFIPS":"37025","pop":216453,"date":"2020-07-17","deaths":33,"County Name":"Cabarrus County","State":"NC","stateFIPS":"37","case_count":1828,"delta":33,"per_delta":0.0184,"r_t":0.7287,"infect_prob":1.8618,"r_t_three":0.7684,"r_t_seven":1.0326,"doubling":23},{"countyFIPS":"37025","pop":216453,"date":"2020-07-18","deaths":33,"County Name":"Cabarrus County","State":"NC","stateFIPS":"37","case_count":1902,"delta":74,"per_delta":0.0405,"r_t":1.6829,"infect_prob":2.0651,"r_t_three":1.0959,"r_t_seven":1.0465,"doubling":23},{"countyFIPS":"37025","pop":216453,"date":"2020-07-19","deaths":34,"County Name":"Cabarrus County","State":"NC","stateFIPS":"37","case_count":1949,"delta":47,"per_delta":0.0247,"r_t":1.064,"infect_prob":1.9727,"r_t_three":1.1585,"r_t_seven":0.9821,"doubling":24},{"countyFIPS":"37025","pop":216453,"date":"2020-07-20","deaths":34,"County Name":"Cabarrus County","State":"NC","stateFIPS":"37","case_count":1970,"delta":21,"per_delta":0.0108,"r_t":0.4716,"infect_prob":1.7972,"r_t_three":1.0728,"r_t_seven":0.9265,"doubling":24},{"countyFIPS":"37025","pop":216453,"date":"2020-07-21","deaths":35,"County Name":"Cabarrus County","State":"NC","stateFIPS":"37","case_count":1989,"delta":19,"per_delta":0.0096,"r_t":0.4354,"infect_prob":1.6077,"r_t_three":0.657,"r_t_seven":0.8513,"doubling":25},{"countyFIPS":"37025","pop":216453,"date":"2020-07-22","deaths":35,"County Name":"Cabarrus County","State":"NC","stateFIPS":"37","case_count":2028,"delta":39,"per_delta":0.0196,"r_t":0.9376,"infect_prob":1.617,"r_t_three":0.6148,"r_t_seven":0.8852,"doubling":26},{"countyFIPS":"37025","pop":216453,"date":"2020-07-23","deaths":37,"County Name":"Cabarrus County","State":"NC","stateFIPS":"37","case_count":2050,"delta":22,"per_delta":0.0108,"r_t":0.5649,"infect_prob":1.5153,"r_t_three":0.646,"r_t_seven":0.8407,"doubling":26},{"countyFIPS":"37025","pop":216453,"date":"2020-07-24","deaths":37,"County Name":"Cabarrus County","State":"NC","stateFIPS":"37","case_count":2094,"delta":44,"per_delta":0.0215,"r_t":1.2146,"infect_prob":1.5662,"r_t_three":0.9057,"r_t_seven":0.9101,"doubling":27},{"countyFIPS":"37025","pop":216453,"date":"2020-07-25","deaths":38,"County Name":"Cabarrus County","State":"NC","stateFIPS":"37","case_count":2129,"delta":35,"per_delta":0.0167,"r_t":1.0157,"infect_prob":1.5384,"r_t_three":0.9317,"r_t_seven":0.8148,"doubling":27},{"countyFIPS":"37025","pop":216453,"date":"2020-07-26","deaths":38,"County Name":"Cabarrus County","State":"NC","stateFIPS":"37","case_count":2164,"delta":35,"per_delta":0.0164,"r_t":1.0406,"infect_prob":1.5477,"r_t_three":1.0903,"r_t_seven":0.8115,"doubling":28},{"countyFIPS":"37025","pop":216453,"date":"2020-07-27","deaths":38,"County Name":"Cabarrus County","State":"NC","stateFIPS":"37","case_count":2184,"delta":20,"per_delta":0.0092,"r_t":0.6021,"infect_prob":1.2982,"r_t_three":0.8861,"r_t_seven":0.8301,"doubling":29},{"countyFIPS":"37025","pop":216453,"date":"2020-07-28","deaths":38,"County Name":"Cabarrus County","State":"NC","stateFIPS":"37","case_count":2212,"delta":28,"per_delta":0.0128,"r_t":0.8603,"infect_prob":1.2104,"r_t_three":0.8343,"r_t_seven":0.8908,"doubling":29},{"countyFIPS":"37025","pop":216453,"date":"2020-07-29","deaths":41,"County Name":"Cabarrus County","State":"NC","stateFIPS":"37","case_count":2248,"delta":36,"per_delta":0.0163,"r_t":1.13,"infect_prob":1.2797,"r_t_three":0.8641,"r_t_seven":0.9183,"doubling":29},{"countyFIPS":"37025","pop":216453,"date":"2020-07-30","deaths":41,"County Name":"Cabarrus County","State":"NC","stateFIPS":"37","case_count":2316,"delta":68,"per_delta":0.0302,"r_t":2.1082,"infect_prob":1.5061,"r_t_three":1.3662,"r_t_seven":1.1388,"doubling":29},{"countyFIPS":"37025","pop":216453,"date":"2020-07-31","deaths":42,"County Name":"Cabarrus County","State":"NC","stateFIPS":"37","case_count":2342,"delta":26,"per_delta":0.0112,"r_t":0.7663,"infect_prob":1.446,"r_t_three":1.3348,"r_t_seven":1.0747,"doubling":30},{"countyFIPS":"37025","pop":216453,"date":"2020-08-01","deaths":45,"County Name":"Cabarrus County","State":"NC","stateFIPS":"37","case_count":2375,"delta":33,"per_delta":0.0141,"r_t":0.9312,"infect_prob":1.4969,"r_t_three":1.2686,"r_t_seven":1.0627,"doubling":30},{"countyFIPS":"37025","pop":216453,"date":"2020-08-02","deaths":46,"County Name":"Cabarrus County","State":"NC","stateFIPS":"37","case_count":2406,"delta":31,"per_delta":0.0131,"r_t":0.8514,"infect_prob":1.4368,"r_t_three":0.8496,"r_t_seven":1.0356,"doubling":31},{"countyFIPS":"37025","pop":216453,"date":"2020-08-03","deaths":46,"County Name":"Cabarrus County","State":"NC","stateFIPS":"37","case_count":2430,"delta":24,"per_delta":0.01,"r_t":0.6595,"infect_prob":1.386,"r_t_three":0.8141,"r_t_seven":1.0438,"doubling":32},{"countyFIPS":"37025","pop":216453,"date":"2020-08-04","deaths":47,"County Name":"Cabarrus County","State":"NC","stateFIPS":"37","case_count":2466,"delta":36,"per_delta":0.0148,"r_t":1.0143,"infect_prob":1.3906,"r_t_three":0.8418,"r_t_seven":1.0658,"doubling":33},{"countyFIPS":"37025","pop":216453,"date":"2020-08-05","deaths":47,"County Name":"Cabarrus County","State":"NC","stateFIPS":"37","case_count":2490,"delta":24,"per_delta":0.0097,"r_t":0.7023,"infect_prob":1.4091,"r_t_three":0.7921,"r_t_seven":1.0048,"doubling":33},{"countyFIPS":"37025","pop":216453,"date":"2020-08-06","deaths":48,"County Name":"Cabarrus County","State":"NC","stateFIPS":"37","case_count":2520,"delta":30,"per_delta":0.012,"r_t":0.9203,"infect_prob":1.4183,"r_t_three":0.879,"r_t_seven":0.835,"doubling":34},{"countyFIPS":"37025","pop":216453,"date":"2020-08-07","deaths":48,"County Name":"Cabarrus County","State":"NC","stateFIPS":"37","case_count":2549,"delta":29,"per_delta":0.0115,"r_t":0.9285,"infect_prob":1.386,"r_t_three":0.8504,"r_t_seven":0.8582,"doubling":35},{"countyFIPS":"37025","pop":216453,"date":"2020-08-08","deaths":50,"County Name":"Cabarrus County","State":"NC","stateFIPS":"37","case_count":2603,"delta":54,"per_delta":0.0212,"r_t":1.7521,"infect_prob":1.3213,"r_t_three":1.2003,"r_t_seven":0.9755,"doubling":36},{"countyFIPS":"37025","pop":216453,"date":"2020-08-09","deaths":50,"County Name":"Cabarrus County","State":"NC","stateFIPS":"37","case_count":2626,"delta":23,"per_delta":0.0088,"r_t":0.7308,"infect_prob":1.3074,"r_t_three":1.1371,"r_t_seven":0.9583,"doubling":37},{"countyFIPS":"37025","pop":216453,"date":"2020-08-10","deaths":50,"County Name":"Cabarrus County","State":"NC","stateFIPS":"37","case_count":2626,"delta":0,"per_delta":0,"r_t":0,"infect_prob":1.155,"r_t_three":0.8276,"r_t_seven":0.864,"doubling":38},{"countyFIPS":"37025","pop":216453,"date":"2020-08-11","deaths":50,"County Name":"Cabarrus County","State":"NC","stateFIPS":"37","case_count":2655,"delta":29,"per_delta":0.011,"r_t":0.9675,"infect_prob":1.1457,"r_t_three":0.5661,"r_t_seven":0.8573,"doubling":38},{"countyFIPS":"37025","pop":216453,"date":"2020-08-12","deaths":50,"County Name":"Cabarrus County","State":"NC","stateFIPS":"37","case_count":2655,"delta":0,"per_delta":0,"r_t":0,"infect_prob":1.0349,"r_t_three":0.3225,"r_t_seven":0.757,"doubling":39},{"countyFIPS":"37025","pop":216453,"date":"2020-08-13","deaths":50,"County Name":"Cabarrus County","State":"NC","stateFIPS":"37","case_count":2714,"delta":59,"per_delta":0.0222,"r_t":2.3331,"infect_prob":1.1411,"r_t_three":1.1002,"r_t_seven":0.9588,"doubling":39},{"countyFIPS":"37025","pop":216453,"date":"2020-08-14","deaths":50,"County Name":"Cabarrus County","State":"NC","stateFIPS":"37","case_count":2753,"delta":39,"per_delta":0.0144,"r_t":1.5627,"infect_prob":1.2104,"r_t_three":1.2986,"r_t_seven":1.0495,"doubling":39},{"countyFIPS":"37025","pop":216453,"date":"2020-08-15","deaths":50,"County Name":"Cabarrus County","State":"NC","stateFIPS":"37","case_count":2767,"delta":14,"per_delta":0.0051,"r_t":0.5444,"infect_prob":1.1365,"r_t_three":1.4801,"r_t_seven":0.8769,"doubling":40},{"countyFIPS":"37025","pop":216453,"date":"2020-08-16","deaths":50,"County Name":"Cabarrus County","State":"NC","stateFIPS":"37","case_count":2803,"delta":36,"per_delta":0.013,"r_t":1.3455,"infect_prob":1.1688,"r_t_three":1.1508,"r_t_seven":0.9647,"doubling":40},{"countyFIPS":"37025","pop":216453,"date":"2020-08-17","deaths":50,"County Name":"Cabarrus County","State":"NC","stateFIPS":"37","case_count":2809,"delta":6,"per_delta":0.0021,"r_t":0.2182,"infect_prob":0.9517,"r_t_three":0.7027,"r_t_seven":0.9959,"doubling":41},{"countyFIPS":"37025","pop":216453,"date":"2020-08-18","deaths":50,"County Name":"Cabarrus County","State":"NC","stateFIPS":"37","case_count":2828,"delta":19,"per_delta":0.0068,"r_t":0.7057,"infect_prob":0.9332,"r_t_three":0.7564,"r_t_seven":0.9585,"doubling":42},{"countyFIPS":"37025","pop":216453,"date":"2020-08-19","deaths":50,"County Name":"Cabarrus County","State":"NC","stateFIPS":"37","case_count":2840,"delta":12,"per_delta":0.0042,"r_t":0.4743,"infect_prob":0.984,"r_t_three":0.4661,"r_t_seven":1.0263,"doubling":43},{"countyFIPS":"37025","pop":216453,"date":"2020-08-20","deaths":51,"County Name":"Cabarrus County","State":"NC","stateFIPS":"37","case_count":2866,"delta":26,"per_delta":0.0092,"r_t":1.1213,"infect_prob":0.9702,"r_t_three":0.7671,"r_t_seven":0.8531,"doubling":43},{"countyFIPS":"37025","pop":216453,"date":"2020-08-21","deaths":51,"County Name":"Cabarrus County","State":"NC","stateFIPS":"37","case_count":2906,"delta":40,"per_delta":0.014,"r_t":1.8236,"infect_prob":1.155,"r_t_three":1.1397,"r_t_seven":0.8904,"doubling":44},{"countyFIPS":"37025","pop":216453,"date":"2020-08-22","deaths":51,"County Name":"Cabarrus County","State":"NC","stateFIPS":"37","case_count":2929,"delta":23,"per_delta":0.0079,"r_t":1.0454,"infect_prob":0.9887,"r_t_three":1.3301,"r_t_seven":0.962,"doubling":44},{"countyFIPS":"37025","pop":216453,"date":"2020-08-23","deaths":51,"County Name":"Cabarrus County","State":"NC","stateFIPS":"37","case_count":2958,"delta":29,"per_delta":0.0099,"r_t":1.2685,"infect_prob":0.9471,"r_t_three":1.3792,"r_t_seven":0.951,"doubling":45},{"countyFIPS":"37025","pop":216453,"date":"2020-08-24","deaths":51,"County Name":"Cabarrus County","State":"NC","stateFIPS":"37","case_count":2986,"delta":28,"per_delta":0.0095,"r_t":1.1563,"infect_prob":1.0118,"r_t_three":1.1567,"r_t_seven":1.085,"doubling":46},{"countyFIPS":"37025","pop":216453,"date":"2020-08-25","deaths":51,"County Name":"Cabarrus County","State":"NC","stateFIPS":"37","case_count":3014,"delta":28,"per_delta":0.0094,"r_t":1.0942,"infect_prob":0.9748,"r_t_three":1.173,"r_t_seven":1.1405,"doubling":47},{"countyFIPS":"37025","pop":216453,"date":"2020-08-26","deaths":51,"County Name":"Cabarrus County","State":"NC","stateFIPS":"37","case_count":3029,"delta":15,"per_delta":0.005,"r_t":0.5688,"infect_prob":1.0118,"r_t_three":0.9398,"r_t_seven":1.154,"doubling":48},{"countyFIPS":"37025","pop":216453,"date":"2020-08-27","deaths":52,"County Name":"Cabarrus County","State":"NC","stateFIPS":"37","case_count":3069,"delta":40,"per_delta":0.0132,"r_t":1.5023,"infect_prob":1.1088,"r_t_three":1.0551,"r_t_seven":1.2084,"doubling":48},{"countyFIPS":"37025","pop":216453,"date":"2020-08-28","deaths":52,"County Name":"Cabarrus County","State":"NC","stateFIPS":"37","case_count":3094,"delta":25,"per_delta":0.0081,"r_t":0.9272,"infect_prob":1.1688,"r_t_three":0.9994,"r_t_seven":1.0804,"doubling":49},{"countyFIPS":"37025","pop":216453,"date":"2020-08-29","deaths":53,"County Name":"Cabarrus County","State":"NC","stateFIPS":"37","case_count":3136,"delta":42,"per_delta":0.0136,"r_t":1.5264,"infect_prob":1.2428,"r_t_three":1.3186,"r_t_seven":1.1491,"doubling":50},{"countyFIPS":"37025","pop":216453,"date":"2020-08-30","deaths":53,"County Name":"Cabarrus County","State":"NC","stateFIPS":"37","case_count":3142,"delta":6,"per_delta":0.0019,"r_t":0.2142,"infect_prob":1.0857,"r_t_three":0.8893,"r_t_seven":0.9985,"doubling":51},{"countyFIPS":"37025","pop":216453,"date":"2020-08-31","deaths":54,"County Name":"Cabarrus County","State":"NC","stateFIPS":"37","case_count":3169,"delta":27,"per_delta":0.0086,"r_t":0.9763,"infect_prob":1.1042,"r_t_three":0.9056,"r_t_seven":0.9728,"doubling":51},{"countyFIPS":"37025","pop":216453,"date":"2020-09-01","deaths":54,"County Name":"Cabarrus County","State":"NC","stateFIPS":"37","case_count":3221,"delta":52,"per_delta":0.0164,"r_t":1.8809,"infect_prob":1.2104,"r_t_three":1.0238,"r_t_seven":1.0852,"doubling":52},{"countyFIPS":"37025","pop":216453,"date":"2020-09-02","deaths":54,"County Name":"Cabarrus County","State":"NC","stateFIPS":"37","case_count":3255,"delta":34,"per_delta":0.0106,"r_t":1.1878,"infect_prob":1.2381,"r_t_three":1.3483,"r_t_seven":1.1736,"doubling":53},{"countyFIPS":"37025","pop":216453,"date":"2020-09-03","deaths":54,"County Name":"Cabarrus County","State":"NC","stateFIPS":"37","case_count":3308,"delta":53,"per_delta":0.0163,"r_t":1.7389,"infect_prob":1.3536,"r_t_three":1.6026,"r_t_seven":1.2074,"doubling":53},{"countyFIPS":"37025","pop":216453,"date":"2020-09-04","deaths":54,"County Name":"Cabarrus County","State":"NC","stateFIPS":"37","case_count":3308,"delta":0,"per_delta":0,"r_t":0,"infect_prob":1.2843,"r_t_three":0.9756,"r_t_seven":1.0749,"doubling":54},{"countyFIPS":"37025","pop":216453,"date":"2020-09-05","deaths":55,"County Name":"Cabarrus County","State":"NC","stateFIPS":"37","case_count":3391,"delta":83,"per_delta":0.0251,"r_t":2.4579,"infect_prob":1.483,"r_t_three":1.399,"r_t_seven":1.208,"doubling":54},{"countyFIPS":"37025","pop":216453,"date":"2020-09-06","deaths":55,"County Name":"Cabarrus County","State":"NC","stateFIPS":"37","case_count":3413,"delta":22,"per_delta":0.0065,"r_t":0.6103,"infect_prob":1.4691,"r_t_three":1.0227,"r_t_seven":1.2646,"doubling":55},{"countyFIPS":"37025","pop":216453,"date":"2020-09-07","deaths":55,"County Name":"Cabarrus County","State":"NC","stateFIPS":"37","case_count":3430,"delta":17,"per_delta":0.005,"r_t":0.4596,"infect_prob":1.3536,"r_t_three":1.1759,"r_t_seven":1.1908,"doubling":56},{"countyFIPS":"37025","pop":216453,"date":"2020-09-08","deaths":56,"County Name":"Cabarrus County","State":"NC","stateFIPS":"37","case_count":3445,"delta":15,"per_delta":0.0044,"r_t":0.4158,"infect_prob":1.3952,"r_t_three":0.4952,"r_t_seven":0.9815,"doubling":56},{"countyFIPS":"37025","pop":216453,"date":"2020-09-09","deaths":56,"County Name":"Cabarrus County","State":"NC","stateFIPS":"37","case_count":3467,"delta":22,"per_delta":0.0064,"r_t":0.6542,"infect_prob":1.3721,"r_t_three":0.5099,"r_t_seven":0.9052,"doubling":57},{"countyFIPS":"37025","pop":216453,"date":"2020-09-10","deaths":56,"County Name":"Cabarrus County","State":"NC","stateFIPS":"37","case_count":3495,"delta":28,"per_delta":0.0081,"r_t":0.9139,"infect_prob":1.2612,"r_t_three":0.6613,"r_t_seven":0.7874,"doubling":58},{"countyFIPS":"37025","pop":216453,"date":"2020-09-11","deaths":56,"County Name":"Cabarrus County","State":"NC","stateFIPS":"37","case_count":3524,"delta":29,"per_delta":0.0083,"r_t":1.033,"infect_prob":1.2381,"r_t_three":0.8671,"r_t_seven":0.935,"doubling":58},{"countyFIPS":"37025","pop":216453,"date":"2020-09-12","deaths":57,"County Name":"Cabarrus County","State":"NC","stateFIPS":"37","case_count":3565,"delta":41,"per_delta":0.0116,"r_t":1.5328,"infect_prob":1.1827,"r_t_three":1.1599,"r_t_seven":0.8028,"doubling":59},{"countyFIPS":"37025","pop":216453,"date":"2020-09-13","deaths":58,"County Name":"Cabarrus County","State":"NC","stateFIPS":"37","case_count":3588,"delta":23,"per_delta":0.0065,"r_t":0.8604,"infect_prob":1.289,"r_t_three":1.1421,"r_t_seven":0.8385,"doubling":60}]
